{
"meta":{"test_sets":[],"test_metrics":[],"learn_metrics":[{"best_value":"Min","name":"MultiClass"}],"launch_mode":"Train","parameters":"","iteration_count":1000,"learn_sets":["learn"],"name":"experiment"},
"iterations":[
{"learn":[2.379538004],"iteration":0,"passed_time":2.867644768,"remaining_time":2864.777123},
{"learn":[2.340626359],"iteration":1,"passed_time":5.381226219,"remaining_time":2685.231883},
{"learn":[2.309321038],"iteration":2,"passed_time":7.781749088,"remaining_time":2586.134614},
{"learn":[2.286286137],"iteration":3,"passed_time":10.48157069,"remaining_time":2609.911102},
{"learn":[2.265366673],"iteration":4,"passed_time":13.19604588,"remaining_time":2626.013131},
{"learn":[2.249595298],"iteration":5,"passed_time":15.84075518,"remaining_time":2624.285108},
{"learn":[2.234317259],"iteration":6,"passed_time":18.36694086,"remaining_time":2605.481754},
{"learn":[2.219888501],"iteration":7,"passed_time":20.81561411,"remaining_time":2581.13615},
{"learn":[2.20736818],"iteration":8,"passed_time":23.19141178,"remaining_time":2553.63212},
{"learn":[2.196620153],"iteration":9,"passed_time":25.68110597,"remaining_time":2542.429491},
{"learn":[2.186797533],"iteration":10,"passed_time":28.24789958,"remaining_time":2539.742971},
{"learn":[2.178724764],"iteration":11,"passed_time":30.87650812,"remaining_time":2542.165835},
{"learn":[2.171284768],"iteration":12,"passed_time":33.55579892,"remaining_time":2547.659502},
{"learn":[2.16296677],"iteration":13,"passed_time":36.3404247,"remaining_time":2559.404197},
{"learn":[2.156085542],"iteration":14,"passed_time":38.86134735,"remaining_time":2551.895142},
{"learn":[2.149331184],"iteration":15,"passed_time":41.27084355,"remaining_time":2538.156879},
{"learn":[2.142441665],"iteration":16,"passed_time":43.86384133,"remaining_time":2536.362119},
{"learn":[2.137554485],"iteration":17,"passed_time":46.42874696,"remaining_time":2532.946084},
{"learn":[2.13216623],"iteration":18,"passed_time":49.32634631,"remaining_time":2546.797144},
{"learn":[2.127336665],"iteration":19,"passed_time":52.16837231,"remaining_time":2556.250243},
{"learn":[2.122840452],"iteration":20,"passed_time":55.06717893,"remaining_time":2567.179437},
{"learn":[2.119751131],"iteration":21,"passed_time":58.00257504,"remaining_time":2578.478109},
{"learn":[2.114756057],"iteration":22,"passed_time":61.67237768,"remaining_time":2619.735348},
{"learn":[2.109702314],"iteration":23,"passed_time":64.75134686,"remaining_time":2633.221439},
{"learn":[2.104844334],"iteration":24,"passed_time":68.05041566,"remaining_time":2653.966211},
{"learn":[2.102604165],"iteration":25,"passed_time":70.85562152,"remaining_time":2654.360591},
{"learn":[2.098273353],"iteration":26,"passed_time":73.65198032,"remaining_time":2654.199142},
{"learn":[2.092811131],"iteration":27,"passed_time":76.86887676,"remaining_time":2668.44815},
{"learn":[2.088909606],"iteration":28,"passed_time":80.44756727,"remaining_time":2693.606476},
{"learn":[2.085603],"iteration":29,"passed_time":84.23789841,"remaining_time":2723.692049},
{"learn":[2.081852012],"iteration":30,"passed_time":88.42390826,"remaining_time":2763.960229},
{"learn":[2.077290227],"iteration":31,"passed_time":94.4589767,"remaining_time":2857.384045},
{"learn":[2.07174224],"iteration":32,"passed_time":98.56603474,"remaining_time":2888.283503},
{"learn":[2.067886886],"iteration":33,"passed_time":102.3950305,"remaining_time":2909.223514},
{"learn":[2.064421142],"iteration":34,"passed_time":107.1167117,"remaining_time":2953.360766},
{"learn":[2.058352728],"iteration":35,"passed_time":111.6145608,"remaining_time":2988.789907},
{"learn":[2.054498427],"iteration":36,"passed_time":115.6166602,"remaining_time":3009.157939},
{"learn":[2.051721363],"iteration":37,"passed_time":119.9546907,"remaining_time":3036.747697},
{"learn":[2.047037576],"iteration":38,"passed_time":123.6369783,"remaining_time":3046.541954},
{"learn":[2.043467894],"iteration":39,"passed_time":127.7593776,"remaining_time":3066.225061},
{"learn":[2.040105215],"iteration":40,"passed_time":132.347765,"remaining_time":3095.646504},
{"learn":[2.03649788],"iteration":41,"passed_time":136.7357739,"remaining_time":3118.877891},
{"learn":[2.03332981],"iteration":42,"passed_time":141.6822943,"remaining_time":3153.254782},
{"learn":[2.030041673],"iteration":43,"passed_time":146.4212213,"remaining_time":3181.333808},
{"learn":[2.025730021],"iteration":44,"passed_time":151.7883359,"remaining_time":3221.285795},
{"learn":[2.023192367],"iteration":45,"passed_time":155.6047274,"remaining_time":3227.106737},
{"learn":[2.019984327],"iteration":46,"passed_time":159.4657396,"remaining_time":3233.422337},
{"learn":[2.016767236],"iteration":47,"passed_time":163.6899164,"remaining_time":3246.516675},
{"learn":[2.013164645],"iteration":48,"passed_time":167.5816609,"remaining_time":3252.452235},
{"learn":[2.009647791],"iteration":49,"passed_time":171.5614312,"remaining_time":3259.667193},
{"learn":[2.005856002],"iteration":50,"passed_time":176.2756817,"remaining_time":3280.110235},
{"learn":[2.003579688],"iteration":51,"passed_time":179.9727586,"remaining_time":3281.041829},
{"learn":[2.000964365],"iteration":52,"passed_time":184.1246728,"remaining_time":3289.925757},
{"learn":[1.998547654],"iteration":53,"passed_time":188.4363027,"remaining_time":3301.124859},
{"learn":[1.996048783],"iteration":54,"passed_time":192.1775685,"remaining_time":3301.960041},
{"learn":[1.992970375],"iteration":55,"passed_time":196.0728618,"remaining_time":3305.228242},
{"learn":[1.991382556],"iteration":56,"passed_time":199.2548376,"remaining_time":3296.444068},
{"learn":[1.988309374],"iteration":57,"passed_time":202.4719301,"remaining_time":3288.423416},
{"learn":[1.984824405],"iteration":58,"passed_time":205.750442,"remaining_time":3281.545185},
{"learn":[1.982548398],"iteration":59,"passed_time":209.3779523,"remaining_time":3280.254586},
{"learn":[1.979996457],"iteration":60,"passed_time":213.7381681,"remaining_time":3290.166226},
{"learn":[1.977241892],"iteration":61,"passed_time":218.8728032,"remaining_time":3311.3337},
{"learn":[1.974197501],"iteration":62,"passed_time":223.9818053,"remaining_time":3331.284945},
{"learn":[1.972012191],"iteration":63,"passed_time":227.9423541,"remaining_time":3333.656928},
{"learn":[1.970367641],"iteration":64,"passed_time":232.8387628,"remaining_time":3349.296049},
{"learn":[1.966898764],"iteration":65,"passed_time":237.2509694,"remaining_time":3357.460689},
{"learn":[1.965334326],"iteration":66,"passed_time":241.8784298,"remaining_time":3368.247388},
{"learn":[1.96358723],"iteration":67,"passed_time":245.3278731,"remaining_time":3362.434966},
{"learn":[1.96064568],"iteration":68,"passed_time":248.8666287,"remaining_time":3357.896107},
{"learn":[1.95815464],"iteration":69,"passed_time":252.4349761,"remaining_time":3353.778968},
{"learn":[1.955493527],"iteration":70,"passed_time":256.2615792,"remaining_time":3353.056438},
{"learn":[1.953333847],"iteration":71,"passed_time":259.8582528,"remaining_time":3349.284147},
{"learn":[1.951026012],"iteration":72,"passed_time":263.8388207,"remaining_time":3350.391599},
{"learn":[1.949441335],"iteration":73,"passed_time":267.2651566,"remaining_time":3344.426149},
{"learn":[1.948060345],"iteration":74,"passed_time":271.081996,"remaining_time":3343.344618},
{"learn":[1.945453074],"iteration":75,"passed_time":274.1517046,"remaining_time":3333.107566},
{"learn":[1.942332359],"iteration":76,"passed_time":278.3327422,"remaining_time":3336.378195},
{"learn":[1.939399428],"iteration":77,"passed_time":282.9824451,"remaining_time":3344.997621},
{"learn":[1.93767959],"iteration":78,"passed_time":286.9720772,"remaining_time":3345.585862},
{"learn":[1.934845638],"iteration":79,"passed_time":291.0003592,"remaining_time":3346.504131},
{"learn":[1.933202101],"iteration":80,"passed_time":294.3974475,"remaining_time":3340.138942},
{"learn":[1.931216068],"iteration":81,"passed_time":298.1385179,"remaining_time":3337.697066},
{"learn":[1.929104659],"iteration":82,"passed_time":301.6948196,"remaining_time":3333.182525},
{"learn":[1.926750426],"iteration":83,"passed_time":305.092204,"remaining_time":3326.957844},
{"learn":[1.924859782],"iteration":84,"passed_time":308.2914233,"remaining_time":3318.666498},
{"learn":[1.923335946],"iteration":85,"passed_time":311.7095092,"remaining_time":3312.819668},
{"learn":[1.921224712],"iteration":86,"passed_time":314.9641187,"remaining_time":3305.313107},
{"learn":[1.918985256],"iteration":87,"passed_time":318.3558957,"remaining_time":3299.324737},
{"learn":[1.917105463],"iteration":88,"passed_time":321.749948,"remaining_time":3293.418007},
{"learn":[1.914995497],"iteration":89,"passed_time":324.8643902,"remaining_time":3284.739945},
{"learn":[1.913273598],"iteration":90,"passed_time":328.1001946,"remaining_time":3277.39645},
{"learn":[1.911282553],"iteration":91,"passed_time":331.312623,"remaining_time":3269.91154},
{"learn":[1.908358496],"iteration":92,"passed_time":334.6443082,"remaining_time":3263.681587},
{"learn":[1.90659106],"iteration":93,"passed_time":338.0810998,"remaining_time":3258.526344},
{"learn":[1.90306414],"iteration":94,"passed_time":341.3231946,"remaining_time":3251.552538},
{"learn":[1.901140611],"iteration":95,"passed_time":344.4365353,"remaining_time":3243.444041},
{"learn":[1.899190802],"iteration":96,"passed_time":347.641732,"remaining_time":3236.29365},
{"learn":[1.897703121],"iteration":97,"passed_time":351.1661308,"remaining_time":3232.161735},
{"learn":[1.894977427],"iteration":98,"passed_time":354.4315888,"remaining_time":3225.68547},
{"learn":[1.893446009],"iteration":99,"passed_time":357.7342556,"remaining_time":3219.608301},
{"learn":[1.891617752],"iteration":100,"passed_time":361.0399195,"remaining_time":3213.612749},
{"learn":[1.889885192],"iteration":101,"passed_time":364.586608,"remaining_time":3209.791901},
{"learn":[1.887968374],"iteration":102,"passed_time":368.0642342,"remaining_time":3205.374933},
{"learn":[1.886481686],"iteration":103,"passed_time":371.2379851,"remaining_time":3198.358026},
{"learn":[1.884528596],"iteration":104,"passed_time":374.444611,"remaining_time":3191.694542},
{"learn":[1.88375564],"iteration":105,"passed_time":377.6022749,"remaining_time":3184.683337},
{"learn":[1.880935895],"iteration":106,"passed_time":380.8185554,"remaining_time":3178.233365},
{"learn":[1.878543106],"iteration":107,"passed_time":383.8731622,"remaining_time":3170.50797},
{"learn":[1.876677731],"iteration":108,"passed_time":387.1187049,"remaining_time":3164.429047},
{"learn":[1.875297291],"iteration":109,"passed_time":390.3518839,"remaining_time":3158.301606},
{"learn":[1.873222253],"iteration":110,"passed_time":393.536677,"remaining_time":3151.838791},
{"learn":[1.871641057],"iteration":111,"passed_time":396.6444238,"remaining_time":3144.823646},
{"learn":[1.868732238],"iteration":112,"passed_time":399.8324198,"remaining_time":3138.507579},
{"learn":[1.867072317],"iteration":113,"passed_time":402.9659719,"remaining_time":3131.823255},
{"learn":[1.864679839],"iteration":114,"passed_time":406.0519409,"remaining_time":3124.834502},
{"learn":[1.86241303],"iteration":115,"passed_time":409.261068,"remaining_time":3118.851588},
{"learn":[1.860764929],"iteration":116,"passed_time":412.517781,"remaining_time":3113.275219},
{"learn":[1.858390335],"iteration":117,"passed_time":415.9493538,"remaining_time":3109.04517},
{"learn":[1.856596241],"iteration":118,"passed_time":419.1202043,"remaining_time":3102.898319},
{"learn":[1.854248139],"iteration":119,"passed_time":422.5794903,"remaining_time":3098.916262},
{"learn":[1.852740247],"iteration":120,"passed_time":425.8682771,"remaining_time":3093.704261},
{"learn":[1.85059049],"iteration":121,"passed_time":429.0889864,"remaining_time":3088.033853},
{"learn":[1.848587854],"iteration":122,"passed_time":432.4111286,"remaining_time":3083.126503},
{"learn":[1.846793414],"iteration":123,"passed_time":435.7269502,"remaining_time":3078.200068},
{"learn":[1.844784903],"iteration":124,"passed_time":438.9614735,"remaining_time":3072.730315},
{"learn":[1.843283086],"iteration":125,"passed_time":442.1924795,"remaining_time":3067.271643},
{"learn":[1.842209341],"iteration":126,"passed_time":445.4215655,"remaining_time":3061.834856},
{"learn":[1.840893055],"iteration":127,"passed_time":448.7217875,"remaining_time":3056.917178},
{"learn":[1.839425085],"iteration":128,"passed_time":451.9946621,"remaining_time":3051.839928},
{"learn":[1.837067165],"iteration":129,"passed_time":455.1570924,"remaining_time":3046.05131},
{"learn":[1.83539237],"iteration":130,"passed_time":458.3088076,"remaining_time":3040.231709},
{"learn":[1.833406783],"iteration":131,"passed_time":461.3598787,"remaining_time":3033.790717},
{"learn":[1.832099198],"iteration":132,"passed_time":464.4041775,"remaining_time":3027.356556},
{"learn":[1.830645983],"iteration":133,"passed_time":467.683675,"remaining_time":3022.493004},
{"learn":[1.829230765],"iteration":134,"passed_time":470.9243871,"remaining_time":3017.404406},
{"learn":[1.827779078],"iteration":135,"passed_time":474.0543089,"remaining_time":3011.639139},
{"learn":[1.826244448],"iteration":136,"passed_time":477.4311996,"remaining_time":3007.468068},
{"learn":[1.824630859],"iteration":137,"passed_time":480.6520542,"remaining_time":3002.333846},
{"learn":[1.823032125],"iteration":138,"passed_time":483.4318072,"remaining_time":2994.494863},
{"learn":[1.821557944],"iteration":139,"passed_time":486.2246725,"remaining_time":2986.808702},
{"learn":[1.819914835],"iteration":140,"passed_time":489.6009182,"remaining_time":2982.746019},
{"learn":[1.819008832],"iteration":141,"passed_time":492.4163304,"remaining_time":2975.304306},
{"learn":[1.816530499],"iteration":142,"passed_time":495.2862961,"remaining_time":2968.254236},
{"learn":[1.814490667],"iteration":143,"passed_time":498.6995657,"remaining_time":2964.491863},
{"learn":[1.813200938],"iteration":144,"passed_time":502.5807714,"remaining_time":2963.493514},
{"learn":[1.811194796],"iteration":145,"passed_time":505.9181753,"remaining_time":2959.274806},
{"learn":[1.80984253],"iteration":146,"passed_time":509.8748874,"remaining_time":2958.661762},
{"learn":[1.808486715],"iteration":147,"passed_time":513.4178975,"remaining_time":2955.62195},
{"learn":[1.807434661],"iteration":148,"passed_time":516.8147858,"remaining_time":2951.740824},
{"learn":[1.805389575],"iteration":149,"passed_time":520.0603307,"remaining_time":2947.00854},
{"learn":[1.803758333],"iteration":150,"passed_time":523.176597,"remaining_time":2941.569078},
{"learn":[1.802191224],"iteration":151,"passed_time":526.3451633,"remaining_time":2936.451964},
{"learn":[1.800372814],"iteration":152,"passed_time":530.1662958,"remaining_time":2934.972892},
{"learn":[1.799489943],"iteration":153,"passed_time":534.0399721,"remaining_time":2933.752055},
{"learn":[1.797908676],"iteration":154,"passed_time":538.0636866,"remaining_time":2933.314936},
{"learn":[1.796737229],"iteration":155,"passed_time":541.9247222,"remaining_time":2931.951702},
{"learn":[1.795424081],"iteration":156,"passed_time":546.9039182,"remaining_time":2936.560529},
{"learn":[1.794312823],"iteration":157,"passed_time":550.8697463,"remaining_time":2935.647635},
{"learn":[1.792767922],"iteration":158,"passed_time":554.8363121,"remaining_time":2934.700242},
{"learn":[1.791230755],"iteration":159,"passed_time":559.0635068,"remaining_time":2935.083411},
{"learn":[1.789840061],"iteration":160,"passed_time":563.9865348,"remaining_time":2939.03542},
{"learn":[1.788295965],"iteration":161,"passed_time":567.794765,"remaining_time":2937.111192},
{"learn":[1.786793876],"iteration":162,"passed_time":571.3096398,"remaining_time":2933.657476},
{"learn":[1.786103956],"iteration":163,"passed_time":576.6416012,"remaining_time":2939.465723},
{"learn":[1.784976323],"iteration":164,"passed_time":579.8468661,"remaining_time":2934.376565},
{"learn":[1.783051176],"iteration":165,"passed_time":583.2681799,"remaining_time":2930.395554},
{"learn":[1.780161995],"iteration":166,"passed_time":586.4358656,"remaining_time":2925.156144},
{"learn":[1.77806811],"iteration":167,"passed_time":590.9618174,"remaining_time":2926.668048},
{"learn":[1.77641239],"iteration":168,"passed_time":595.7229857,"remaining_time":2929.265096},
{"learn":[1.775233453],"iteration":169,"passed_time":599.9582976,"remaining_time":2929.208159},
{"learn":[1.774136683],"iteration":170,"passed_time":603.878914,"remaining_time":2927.576723},
{"learn":[1.772546686],"iteration":171,"passed_time":608.0678538,"remaining_time":2927.210366},
{"learn":[1.77163566],"iteration":172,"passed_time":611.9932481,"remaining_time":2925.539978},
{"learn":[1.769272807],"iteration":173,"passed_time":616.0646041,"remaining_time":2924.536569},
{"learn":[1.767521461],"iteration":174,"passed_time":620.1559495,"remaining_time":2923.592334},
{"learn":[1.766031971],"iteration":175,"passed_time":624.127463,"remaining_time":2922.051304},
{"learn":[1.765028028],"iteration":176,"passed_time":627.9612605,"remaining_time":2919.842471},
{"learn":[1.763823983],"iteration":177,"passed_time":631.8500339,"remaining_time":2917.869258},
{"learn":[1.762489606],"iteration":178,"passed_time":635.3669682,"remaining_time":2914.169167},
{"learn":[1.75998825],"iteration":179,"passed_time":638.7902707,"remaining_time":2910.044566},
{"learn":[1.75818222],"iteration":180,"passed_time":642.3236599,"remaining_time":2906.425842},
{"learn":[1.757024984],"iteration":181,"passed_time":645.4525545,"remaining_time":2900.990053},
{"learn":[1.755725201],"iteration":182,"passed_time":649.1954739,"remaining_time":2898.320777},
{"learn":[1.754436813],"iteration":183,"passed_time":652.7248197,"remaining_time":2894.692679},
{"learn":[1.752866485],"iteration":184,"passed_time":655.7977139,"remaining_time":2889.054793},
{"learn":[1.751416847],"iteration":185,"passed_time":658.8711909,"remaining_time":2883.44704},
{"learn":[1.750130257],"iteration":186,"passed_time":662.007556,"remaining_time":2878.139802},
{"learn":[1.748377759],"iteration":187,"passed_time":665.2758217,"remaining_time":2873.425358},
{"learn":[1.747371004],"iteration":188,"passed_time":668.336863,"remaining_time":2867.837015},
{"learn":[1.745720083],"iteration":189,"passed_time":671.5944532,"remaining_time":2863.113195},
{"learn":[1.743993398],"iteration":190,"passed_time":674.6822734,"remaining_time":2857.68565},
{"learn":[1.742610769],"iteration":191,"passed_time":677.799264,"remaining_time":2852.405236},
{"learn":[1.741112272],"iteration":192,"passed_time":680.8360127,"remaining_time":2846.811722},
{"learn":[1.740011351],"iteration":193,"passed_time":683.878051,"remaining_time":2841.266542},
{"learn":[1.738972077],"iteration":194,"passed_time":686.8804645,"remaining_time":2835.583456},
{"learn":[1.737836166],"iteration":195,"passed_time":690.0353619,"remaining_time":2830.553219},
{"learn":[1.736033227],"iteration":196,"passed_time":693.1372403,"remaining_time":2825.325908},
{"learn":[1.734535256],"iteration":197,"passed_time":696.2267827,"remaining_time":2820.0701},
{"learn":[1.733294414],"iteration":198,"passed_time":699.5784106,"remaining_time":2815.890989},
{"learn":[1.732361188],"iteration":199,"passed_time":703.3555876,"remaining_time":2813.42235},
{"learn":[1.730401023],"iteration":200,"passed_time":706.5958856,"remaining_time":2808.80653},
{"learn":[1.729372571],"iteration":201,"passed_time":710.2381755,"remaining_time":2805.792396},
{"learn":[1.727955218],"iteration":202,"passed_time":713.7553596,"remaining_time":2802.280895},
{"learn":[1.72676118],"iteration":203,"passed_time":717.4578164,"remaining_time":2799.492264},
{"learn":[1.725001479],"iteration":204,"passed_time":721.3514828,"remaining_time":2797.436238},
{"learn":[1.723637597],"iteration":205,"passed_time":724.8021389,"remaining_time":2793.654846},
{"learn":[1.721942302],"iteration":206,"passed_time":728.2764184,"remaining_time":2789.967149},
{"learn":[1.719426686],"iteration":207,"passed_time":731.9255791,"remaining_time":2786.947397},
{"learn":[1.717933667],"iteration":208,"passed_time":735.8802698,"remaining_time":2785.077959},
{"learn":[1.716208782],"iteration":209,"passed_time":739.0020779,"remaining_time":2780.055436},
{"learn":[1.714582762],"iteration":210,"passed_time":742.8713039,"remaining_time":2777.845776},
{"learn":[1.713283373],"iteration":211,"passed_time":746.3998125,"remaining_time":2774.35402},
{"learn":[1.711616799],"iteration":212,"passed_time":749.8672291,"remaining_time":2770.636194},
{"learn":[1.710421802],"iteration":213,"passed_time":753.1368296,"remaining_time":2766.19415},
{"learn":[1.709453896],"iteration":214,"passed_time":756.166467,"remaining_time":2760.886868},
{"learn":[1.708381373],"iteration":215,"passed_time":758.99734,"remaining_time":2754.879234},
{"learn":[1.70678481],"iteration":216,"passed_time":762.0971705,"remaining_time":2749.871357},
{"learn":[1.705274683],"iteration":217,"passed_time":765.4936478,"remaining_time":2745.945104},
{"learn":[1.704303275],"iteration":218,"passed_time":768.970071,"remaining_time":2742.308792},
{"learn":[1.703182664],"iteration":219,"passed_time":772.5162321,"remaining_time":2738.921186},
{"learn":[1.702357767],"iteration":220,"passed_time":775.8568936,"remaining_time":2734.807783},
{"learn":[1.700845425],"iteration":221,"passed_time":778.7950314,"remaining_time":2729.290696},
{"learn":[1.699600167],"iteration":222,"passed_time":782.6037328,"remaining_time":2726.830046},
{"learn":[1.698663469],"iteration":223,"passed_time":785.9089345,"remaining_time":2722.613095},
{"learn":[1.697003287],"iteration":224,"passed_time":789.0664065,"remaining_time":2717.8954},
{"learn":[1.695352042],"iteration":225,"passed_time":792.1040029,"remaining_time":2712.780966},
{"learn":[1.693411468],"iteration":226,"passed_time":794.9448304,"remaining_time":2707.014775},
{"learn":[1.6923626],"iteration":227,"passed_time":798.9284436,"remaining_time":2705.143677},
{"learn":[1.691130245],"iteration":228,"passed_time":802.4709886,"remaining_time":2701.769136},
{"learn":[1.689374792],"iteration":229,"passed_time":806.1748985,"remaining_time":2698.933356},
{"learn":[1.688728604],"iteration":230,"passed_time":809.983013,"remaining_time":2696.436957},
{"learn":[1.687652113],"iteration":231,"passed_time":812.9377734,"remaining_time":2691.104353},
{"learn":[1.68690203],"iteration":232,"passed_time":815.8280573,"remaining_time":2685.579914},
{"learn":[1.684663076],"iteration":233,"passed_time":818.8952367,"remaining_time":2680.657057},
{"learn":[1.683377554],"iteration":234,"passed_time":822.0339532,"remaining_time":2675.982869},
{"learn":[1.682410708],"iteration":235,"passed_time":825.8740142,"remaining_time":2673.592148},
{"learn":[1.681431851],"iteration":236,"passed_time":830.2835931,"remaining_time":2673.022707},
{"learn":[1.68073778],"iteration":237,"passed_time":834.3970274,"remaining_time":2671.472836},
{"learn":[1.679733334],"iteration":238,"passed_time":838.5258421,"remaining_time":2669.950485},
{"learn":[1.67878315],"iteration":239,"passed_time":842.946148,"remaining_time":2669.329469},
{"learn":[1.678080008],"iteration":240,"passed_time":847.3103422,"remaining_time":2668.500206},
{"learn":[1.676432428],"iteration":241,"passed_time":851.9583318,"remaining_time":2668.530642},
{"learn":[1.675258515],"iteration":242,"passed_time":855.6769743,"remaining_time":2665.627447},
{"learn":[1.673539696],"iteration":243,"passed_time":859.2031378,"remaining_time":2662.121197},
{"learn":[1.671931421],"iteration":244,"passed_time":862.6705627,"remaining_time":2658.433775},
{"learn":[1.670944622],"iteration":245,"passed_time":866.2905524,"remaining_time":2655.215758},
{"learn":[1.669791549],"iteration":246,"passed_time":870.4668644,"remaining_time":2653.690481},
{"learn":[1.668156008],"iteration":247,"passed_time":874.4453906,"remaining_time":2651.544088},
{"learn":[1.666267895],"iteration":248,"passed_time":877.7577385,"remaining_time":2647.373741},
{"learn":[1.664550685],"iteration":249,"passed_time":880.9572472,"remaining_time":2642.871741},
{"learn":[1.663396785],"iteration":250,"passed_time":884.1480983,"remaining_time":2638.354285},
{"learn":[1.662295974],"iteration":251,"passed_time":887.5167899,"remaining_time":2634.375233},
{"learn":[1.661299511],"iteration":252,"passed_time":890.9554832,"remaining_time":2630.607692},
{"learn":[1.660018651],"iteration":253,"passed_time":894.3136762,"remaining_time":2626.606309},
{"learn":[1.65933549],"iteration":254,"passed_time":897.6040827,"remaining_time":2622.411928},
{"learn":[1.658370365],"iteration":255,"passed_time":901.1881347,"remaining_time":2619.078016},
{"learn":[1.657263371],"iteration":256,"passed_time":904.9516568,"remaining_time":2616.261015},
{"learn":[1.656642188],"iteration":257,"passed_time":908.244392,"remaining_time":2612.082709},
{"learn":[1.655496014],"iteration":258,"passed_time":911.5850918,"remaining_time":2608.048467},
{"learn":[1.654128803],"iteration":259,"passed_time":914.9730282,"remaining_time":2604.154003},
{"learn":[1.653069382],"iteration":260,"passed_time":918.2885978,"remaining_time":2600.05852},
{"learn":[1.65191118],"iteration":261,"passed_time":921.7506963,"remaining_time":2596.381732},
{"learn":[1.650778009],"iteration":262,"passed_time":925.0097782,"remaining_time":2592.137667},
{"learn":[1.649039173],"iteration":263,"passed_time":928.2435095,"remaining_time":2587.83039},
{"learn":[1.64776441],"iteration":264,"passed_time":931.7767432,"remaining_time":2584.36191},
{"learn":[1.646566635],"iteration":265,"passed_time":935.1225764,"remaining_time":2580.375831},
{"learn":[1.645028024],"iteration":266,"passed_time":938.5096841,"remaining_time":2576.507859},
{"learn":[1.644215982],"iteration":267,"passed_time":941.9095863,"remaining_time":2572.678422},
{"learn":[1.643124675],"iteration":268,"passed_time":945.2809099,"remaining_time":2568.774517},
{"learn":[1.641882423],"iteration":269,"passed_time":948.6206914,"remaining_time":2564.789277},
{"learn":[1.64036773],"iteration":270,"passed_time":952.8081005,"remaining_time":2563.088949},
{"learn":[1.639677482],"iteration":271,"passed_time":956.5142636,"remaining_time":2560.082294},
{"learn":[1.638148613],"iteration":272,"passed_time":959.7614233,"remaining_time":2555.848186},
{"learn":[1.637147215],"iteration":273,"passed_time":963.0744044,"remaining_time":2551.795685},
{"learn":[1.636134952],"iteration":274,"passed_time":966.4486445,"remaining_time":2547.910063},
{"learn":[1.634776194],"iteration":275,"passed_time":969.8647602,"remaining_time":2544.137994},
{"learn":[1.633888185],"iteration":276,"passed_time":973.2771226,"remaining_time":2540.358699},
{"learn":[1.632819683],"iteration":277,"passed_time":976.5159696,"remaining_time":2536.131403},
{"learn":[1.632117753],"iteration":278,"passed_time":979.9856476,"remaining_time":2532.507713},
{"learn":[1.631008276],"iteration":279,"passed_time":983.2855034,"remaining_time":2528.448437},
{"learn":[1.629538935],"iteration":280,"passed_time":986.5948331,"remaining_time":2524.418808},
{"learn":[1.628458873],"iteration":281,"passed_time":990.0277124,"remaining_time":2520.708856},
{"learn":[1.627419661],"iteration":282,"passed_time":993.4714823,"remaining_time":2517.028455},
{"learn":[1.626445263],"iteration":283,"passed_time":996.9129668,"remaining_time":2513.343959},
{"learn":[1.625878418],"iteration":284,"passed_time":1001.134643,"remaining_time":2511.618489},
{"learn":[1.624995595],"iteration":285,"passed_time":1005.075763,"remaining_time":2509.175157},
{"learn":[1.623800105],"iteration":286,"passed_time":1008.702689,"remaining_time":2505.940826},
{"learn":[1.622878713],"iteration":287,"passed_time":1012.463538,"remaining_time":2503.034857},
{"learn":[1.621032496],"iteration":288,"passed_time":1016.523933,"remaining_time":2500.859919},
{"learn":[1.620216908],"iteration":289,"passed_time":1020.120274,"remaining_time":2497.535843},
{"learn":[1.618228029],"iteration":290,"passed_time":1023.622562,"remaining_time":2493.980744},
{"learn":[1.616738518],"iteration":291,"passed_time":1027.136096,"remaining_time":2490.453274},
{"learn":[1.61602908],"iteration":292,"passed_time":1030.637156,"remaining_time":2486.895801},
{"learn":[1.615154152],"iteration":293,"passed_time":1033.937553,"remaining_time":2482.856845},
{"learn":[1.614155358],"iteration":294,"passed_time":1036.934688,"remaining_time":2478.098152},
{"learn":[1.612747353],"iteration":295,"passed_time":1039.782117,"remaining_time":2472.995306},
{"learn":[1.610989253],"iteration":296,"passed_time":1043.730854,"remaining_time":2470.514445},
{"learn":[1.61015946],"iteration":297,"passed_time":1047.367661,"remaining_time":2467.288919},
{"learn":[1.609086449],"iteration":298,"passed_time":1051.540046,"remaining_time":2465.316295},
{"learn":[1.608090134],"iteration":299,"passed_time":1055.231185,"remaining_time":2462.206099},
{"learn":[1.60700845],"iteration":300,"passed_time":1059.743804,"remaining_time":2460.999731},
{"learn":[1.605708389],"iteration":301,"passed_time":1063.36044,"remaining_time":2457.70062},
{"learn":[1.60454251],"iteration":302,"passed_time":1066.66969,"remaining_time":2453.692322},
{"learn":[1.603616712],"iteration":303,"passed_time":1070.217345,"remaining_time":2450.234447},
{"learn":[1.602317305],"iteration":304,"passed_time":1074.690111,"remaining_time":2448.884024},
{"learn":[1.60132881],"iteration":305,"passed_time":1079.0428,"remaining_time":2447.240861},
{"learn":[1.600149343],"iteration":306,"passed_time":1083.985476,"remaining_time":2446.91184},
{"learn":[1.598395956],"iteration":307,"passed_time":1088.697703,"remaining_time":2446.035099},
{"learn":[1.597225791],"iteration":308,"passed_time":1092.548648,"remaining_time":2443.207494},
{"learn":[1.595694893],"iteration":309,"passed_time":1096.150735,"remaining_time":2439.819378},
{"learn":[1.594797246],"iteration":310,"passed_time":1099.741235,"remaining_time":2436.404216},
{"learn":[1.593822304],"iteration":311,"passed_time":1103.085892,"remaining_time":2432.445814},
{"learn":[1.59242993],"iteration":312,"passed_time":1106.67621,"remaining_time":2429.03053},
{"learn":[1.591676863],"iteration":313,"passed_time":1110.10517,"remaining_time":2425.261614},
{"learn":[1.590585861],"iteration":314,"passed_time":1113.619048,"remaining_time":2421.679517},
{"learn":[1.589162737],"iteration":315,"passed_time":1116.925607,"remaining_time":2417.649099},
{"learn":[1.587387048],"iteration":316,"passed_time":1120.627478,"remaining_time":2414.474976},
{"learn":[1.586499464],"iteration":317,"passed_time":1124.297985,"remaining_time":2411.23027},
{"learn":[1.58486932],"iteration":318,"passed_time":1127.759369,"remaining_time":2407.536458},
{"learn":[1.583707132],"iteration":319,"passed_time":1131.460522,"remaining_time":2404.35361},
{"learn":[1.582254407],"iteration":320,"passed_time":1134.829451,"remaining_time":2400.464789},
{"learn":[1.581352097],"iteration":321,"passed_time":1138.221375,"remaining_time":2396.627617},
{"learn":[1.580419796],"iteration":322,"passed_time":1141.713333,"remaining_time":2393.002869},
{"learn":[1.579493562],"iteration":323,"passed_time":1145.24791,"remaining_time":2389.467862},
{"learn":[1.577699617],"iteration":324,"passed_time":1148.594153,"remaining_time":2385.541701},
{"learn":[1.576408366],"iteration":325,"passed_time":1152.031466,"remaining_time":2381.807387},
{"learn":[1.575542815],"iteration":326,"passed_time":1155.454147,"remaining_time":2378.044773},
{"learn":[1.574440138],"iteration":327,"passed_time":1158.931989,"remaining_time":2374.397245},
{"learn":[1.573829982],"iteration":328,"passed_time":1162.370315,"remaining_time":2370.670157},
{"learn":[1.572677583],"iteration":329,"passed_time":1165.799858,"remaining_time":2366.926984},
{"learn":[1.571273427],"iteration":330,"passed_time":1169.019163,"remaining_time":2362.760786},
{"learn":[1.570643568],"iteration":331,"passed_time":1172.555902,"remaining_time":2359.238984},
{"learn":[1.56953241],"iteration":332,"passed_time":1176.207391,"remaining_time":2355.946936},
{"learn":[1.568265665],"iteration":333,"passed_time":1179.668955,"remaining_time":2352.274025},
{"learn":[1.566748902],"iteration":334,"passed_time":1183.143872,"remaining_time":2348.628881},
{"learn":[1.565967989],"iteration":335,"passed_time":1187.577674,"remaining_time":2346.87969},
{"learn":[1.564781427],"iteration":336,"passed_time":1192.717403,"remaining_time":2346.503378},
{"learn":[1.563806452],"iteration":337,"passed_time":1196.433225,"remaining_time":2343.310045},
{"learn":[1.563240348],"iteration":338,"passed_time":1199.714347,"remaining_time":2339.266027},
{"learn":[1.562264369],"iteration":339,"passed_time":1202.979783,"remaining_time":2335.19605},
{"learn":[1.561189],"iteration":340,"passed_time":1206.229113,"remaining_time":2331.099663},
{"learn":[1.560269631],"iteration":341,"passed_time":1209.533476,"remaining_time":2327.114115},
{"learn":[1.559635306],"iteration":342,"passed_time":1212.953574,"remaining_time":2323.354221},
{"learn":[1.558611044],"iteration":343,"passed_time":1216.399155,"remaining_time":2319.644901},
{"learn":[1.557872772],"iteration":344,"passed_time":1219.699818,"remaining_time":2315.661974},
{"learn":[1.557089648],"iteration":345,"passed_time":1223.024244,"remaining_time":2311.727906},
{"learn":[1.556487403],"iteration":346,"passed_time":1226.210877,"remaining_time":2307.538049},
{"learn":[1.555550559],"iteration":347,"passed_time":1229.607075,"remaining_time":2303.74659},
{"learn":[1.554971366],"iteration":348,"passed_time":1232.869027,"remaining_time":2299.706982},
{"learn":[1.553699952],"iteration":349,"passed_time":1236.127193,"remaining_time":2295.664787},
{"learn":[1.55301697],"iteration":350,"passed_time":1240.136762,"remaining_time":2293.016406},
{"learn":[1.551804371],"iteration":351,"passed_time":1244.865565,"remaining_time":2291.684336},
{"learn":[1.55119839],"iteration":352,"passed_time":1249.025069,"remaining_time":2289.289574},
{"learn":[1.550393497],"iteration":353,"passed_time":1252.596457,"remaining_time":2285.811613},
{"learn":[1.549400267],"iteration":354,"passed_time":1257.064576,"remaining_time":2283.9624},
{"learn":[1.548914007],"iteration":355,"passed_time":1260.240418,"remaining_time":2279.760756},
{"learn":[1.548450596],"iteration":356,"passed_time":1263.563783,"remaining_time":2275.830568},
{"learn":[1.547663943],"iteration":357,"passed_time":1266.862214,"remaining_time":2271.859055},
{"learn":[1.547062855],"iteration":358,"passed_time":1270.632597,"remaining_time":2268.733968},
{"learn":[1.546208497],"iteration":359,"passed_time":1274.010675,"remaining_time":2264.907867},
{"learn":[1.54544738],"iteration":360,"passed_time":1277.308613,"remaining_time":2260.942393},
{"learn":[1.544386557],"iteration":361,"passed_time":1280.575122,"remaining_time":2256.925215},
{"learn":[1.542603963],"iteration":362,"passed_time":1283.911044,"remaining_time":2253.033981},
{"learn":[1.541881631],"iteration":363,"passed_time":1287.359439,"remaining_time":2249.342317},
{"learn":[1.541313636],"iteration":364,"passed_time":1290.933052,"remaining_time":2245.869831},
{"learn":[1.540616844],"iteration":365,"passed_time":1294.324583,"remaining_time":2242.081382},
{"learn":[1.539708352],"iteration":366,"passed_time":1297.560755,"remaining_time":2238.027134},
{"learn":[1.538570586],"iteration":367,"passed_time":1301.294346,"remaining_time":2234.831594},
{"learn":[1.537617585],"iteration":368,"passed_time":1305.619428,"remaining_time":2232.644604},
{"learn":[1.536612824],"iteration":369,"passed_time":1309.893658,"remaining_time":2230.359471},
{"learn":[1.535780065],"iteration":370,"passed_time":1314.039938,"remaining_time":2227.846688},
{"learn":[1.534635161],"iteration":371,"passed_time":1318.227663,"remaining_time":2225.395087},
{"learn":[1.533988725],"iteration":372,"passed_time":1322.35412,"remaining_time":2222.831188},
{"learn":[1.533304178],"iteration":373,"passed_time":1326.454488,"remaining_time":2220.215266},
{"learn":[1.532160584],"iteration":374,"passed_time":1330.689643,"remaining_time":2217.816071},
{"learn":[1.530891025],"iteration":375,"passed_time":1334.979533,"remaining_time":2215.497949},
{"learn":[1.529369047],"iteration":376,"passed_time":1339.386998,"remaining_time":2213.36366},
{"learn":[1.528566816],"iteration":377,"passed_time":1343.777313,"remaining_time":2211.189124},
{"learn":[1.527376189],"iteration":378,"passed_time":1347.599384,"remaining_time":2208.071814},
{"learn":[1.526573203],"iteration":379,"passed_time":1350.432165,"remaining_time":2203.33669},
{"learn":[1.525530303],"iteration":380,"passed_time":1353.859162,"remaining_time":2199.576959},
{"learn":[1.524740008],"iteration":381,"passed_time":1357.983326,"remaining_time":2196.946847},
{"learn":[1.524139524],"iteration":382,"passed_time":1361.267977,"remaining_time":2192.956506},
{"learn":[1.523375057],"iteration":383,"passed_time":1364.5105,"remaining_time":2188.90226},
{"learn":[1.52218989],"iteration":384,"passed_time":1367.694706,"remaining_time":2184.759076},
{"learn":[1.521014031],"iteration":385,"passed_time":1371.283654,"remaining_time":2181.264673},
{"learn":[1.520244818],"iteration":386,"passed_time":1376.329243,"remaining_time":2180.077069},
{"learn":[1.519353709],"iteration":387,"passed_time":1380.723688,"remaining_time":2177.842518},
{"learn":[1.518323468],"iteration":388,"passed_time":1385.908887,"remaining_time":2176.838895},
{"learn":[1.517527316],"iteration":389,"passed_time":1389.648751,"remaining_time":2173.553174},
{"learn":[1.517049235],"iteration":390,"passed_time":1393.225357,"remaining_time":2170.010851},
{"learn":[1.51583816],"iteration":391,"passed_time":1396.572298,"remaining_time":2166.112136},
{"learn":[1.515426806],"iteration":392,"passed_time":1400.066772,"remaining_time":2162.444098},
{"learn":[1.514437732],"iteration":393,"passed_time":1403.332487,"remaining_time":2158.425094},
{"learn":[1.514090531],"iteration":394,"passed_time":1406.683806,"remaining_time":2154.541019},
{"learn":[1.513090053],"iteration":395,"passed_time":1410.23921,"remaining_time":2150.970916},
{"learn":[1.51232826],"iteration":396,"passed_time":1413.621416,"remaining_time":2147.137819},
{"learn":[1.511757095],"iteration":397,"passed_time":1416.983481,"remaining_time":2143.276521},
{"learn":[1.510451903],"iteration":398,"passed_time":1420.600601,"remaining_time":2139.801907},
{"learn":[1.509645408],"iteration":399,"passed_time":1424.030311,"remaining_time":2136.045467},
{"learn":[1.508376303],"iteration":400,"passed_time":1427.363744,"remaining_time":2132.14684},
{"learn":[1.506880849],"iteration":401,"passed_time":1430.724023,"remaining_time":2128.290959},
{"learn":[1.506351265],"iteration":402,"passed_time":1434.45076,"remaining_time":2124.980407},
{"learn":[1.505448184],"iteration":403,"passed_time":1439.294329,"remaining_time":2123.315397},
{"learn":[1.504512602],"iteration":404,"passed_time":1444.260078,"remaining_time":2121.814188},
{"learn":[1.503534075],"iteration":405,"passed_time":1448.325949,"remaining_time":2118.979344},
{"learn":[1.502769618],"iteration":406,"passed_time":1451.631169,"remaining_time":2115.03018},
{"learn":[1.501500855],"iteration":407,"passed_time":1455.066228,"remaining_time":2111.272566},
{"learn":[1.500847221],"iteration":408,"passed_time":1458.334201,"remaining_time":2107.275092},
{"learn":[1.499938475],"iteration":409,"passed_time":1461.830366,"remaining_time":2103.609551},
{"learn":[1.499043515],"iteration":410,"passed_time":1465.1362,"remaining_time":2099.672072},
{"learn":[1.497868399],"iteration":411,"passed_time":1468.551642,"remaining_time":2095.89409},
{"learn":[1.497232075],"iteration":412,"passed_time":1471.893581,"remaining_time":2092.013395},
{"learn":[1.496657811],"iteration":413,"passed_time":1475.518602,"remaining_time":2088.535993},
{"learn":[1.495570636],"iteration":414,"passed_time":1479.180995,"remaining_time":2085.110559},
{"learn":[1.494397572],"iteration":415,"passed_time":1482.592664,"remaining_time":2081.332008},
{"learn":[1.493681335],"iteration":416,"passed_time":1485.884717,"remaining_time":2077.387986},
{"learn":[1.49321128],"iteration":417,"passed_time":1489.29714,"remaining_time":2073.614678},
{"learn":[1.492670245],"iteration":418,"passed_time":1492.660696,"remaining_time":2069.775332},
{"learn":[1.492116794],"iteration":419,"passed_time":1495.996221,"remaining_time":2065.899543},
{"learn":[1.491565816],"iteration":420,"passed_time":1499.506442,"remaining_time":2062.266579},
{"learn":[1.490540888],"iteration":421,"passed_time":1503.328119,"remaining_time":2059.060789},
{"learn":[1.490070116],"iteration":422,"passed_time":1506.662865,"remaining_time":2055.187879},
{"learn":[1.489179036],"iteration":423,"passed_time":1509.960947,"remaining_time":2051.267702},
{"learn":[1.488358245],"iteration":424,"passed_time":1513.251391,"remaining_time":2047.340118},
{"learn":[1.487358828],"iteration":425,"passed_time":1516.769863,"remaining_time":2043.722773},
{"learn":[1.486404919],"iteration":426,"passed_time":1520.011754,"remaining_time":2039.734742},
{"learn":[1.48584155],"iteration":427,"passed_time":1523.99941,"remaining_time":2036.746876},
{"learn":[1.485240764],"iteration":428,"passed_time":1528.660815,"remaining_time":2034.651108},
{"learn":[1.484796174],"iteration":429,"passed_time":1533.42764,"remaining_time":2032.683151},
{"learn":[1.484204324],"iteration":430,"passed_time":1538.088139,"remaining_time":2030.561835},
{"learn":[1.483064645],"iteration":431,"passed_time":1542.156453,"remaining_time":2027.650152},
{"learn":[1.482335419],"iteration":432,"passed_time":1545.753714,"remaining_time":2024.116295},
{"learn":[1.481669721],"iteration":433,"passed_time":1549.284822,"remaining_time":2020.495874},
{"learn":[1.480434123],"iteration":434,"passed_time":1553.136503,"remaining_time":2017.292239},
{"learn":[1.479253205],"iteration":435,"passed_time":1556.620394,"remaining_time":2013.609867},
{"learn":[1.478131404],"iteration":436,"passed_time":1560.081095,"remaining_time":2009.898527},
{"learn":[1.477565056],"iteration":437,"passed_time":1563.401165,"remaining_time":2006.007888},
{"learn":[1.476592309],"iteration":438,"passed_time":1566.843937,"remaining_time":2002.276649},
{"learn":[1.475928687],"iteration":439,"passed_time":1570.256211,"remaining_time":1998.507905},
{"learn":[1.47545933],"iteration":440,"passed_time":1573.736657,"remaining_time":1994.827191},
{"learn":[1.474591221],"iteration":441,"passed_time":1577.27486,"remaining_time":1991.220298},
{"learn":[1.473742606],"iteration":442,"passed_time":1580.69633,"remaining_time":1987.466944},
{"learn":[1.472978507],"iteration":443,"passed_time":1584.077359,"remaining_time":1983.664441},
{"learn":[1.472369479],"iteration":444,"passed_time":1587.383742,"remaining_time":1979.770734},
{"learn":[1.471618782],"iteration":445,"passed_time":1590.751909,"remaining_time":1975.956407},
{"learn":[1.470897307],"iteration":446,"passed_time":1594.2117,"remaining_time":1972.257427},
{"learn":[1.46964922],"iteration":447,"passed_time":1597.549634,"remaining_time":1968.409371},
{"learn":[1.469110575],"iteration":448,"passed_time":1600.893177,"remaining_time":1964.570469},
{"learn":[1.467817026],"iteration":449,"passed_time":1604.023955,"remaining_time":1960.473723},
{"learn":[1.466816292],"iteration":450,"passed_time":1607.328247,"remaining_time":1956.592478},
{"learn":[1.46571095],"iteration":451,"passed_time":1610.547929,"remaining_time":1952.611206},
{"learn":[1.464538295],"iteration":452,"passed_time":1613.960115,"remaining_time":1948.865746},
{"learn":[1.463644534],"iteration":453,"passed_time":1617.620063,"remaining_time":1945.419723},
{"learn":[1.462648321],"iteration":454,"passed_time":1620.896199,"remaining_time":1941.513029},
{"learn":[1.461767689],"iteration":455,"passed_time":1624.16212,"remaining_time":1937.596915},
{"learn":[1.460865419],"iteration":456,"passed_time":1627.471828,"remaining_time":1933.735673},
{"learn":[1.460027915],"iteration":457,"passed_time":1630.923787,"remaining_time":1930.045181},
{"learn":[1.459184953],"iteration":458,"passed_time":1634.334711,"remaining_time":1926.307361},
{"learn":[1.457849834],"iteration":459,"passed_time":1637.733735,"remaining_time":1922.556993},
{"learn":[1.457396208],"iteration":460,"passed_time":1641.241963,"remaining_time":1918.935831},
{"learn":[1.456611992],"iteration":461,"passed_time":1644.793903,"remaining_time":1915.366061},
{"learn":[1.4560524],"iteration":462,"passed_time":1647.947438,"remaining_time":1911.334286},
{"learn":[1.45507858],"iteration":463,"passed_time":1651.580291,"remaining_time":1907.859992},
{"learn":[1.453913862],"iteration":464,"passed_time":1654.612318,"remaining_time":1903.693742},
{"learn":[1.452734514],"iteration":465,"passed_time":1657.436534,"remaining_time":1899.294226},
{"learn":[1.451902164],"iteration":466,"passed_time":1660.282706,"remaining_time":1894.926515},
{"learn":[1.451151943],"iteration":467,"passed_time":1663.013958,"remaining_time":1890.434671},
{"learn":[1.450570773],"iteration":468,"passed_time":1665.678203,"remaining_time":1885.874469},
{"learn":[1.449981861],"iteration":469,"passed_time":1668.34531,"remaining_time":1881.325562},
{"learn":[1.449107147],"iteration":470,"passed_time":1671.061792,"remaining_time":1876.840101},
{"learn":[1.448252012],"iteration":471,"passed_time":1673.848589,"remaining_time":1872.440794},
{"learn":[1.447623172],"iteration":472,"passed_time":1676.657886,"remaining_time":1868.073374},
{"learn":[1.447001918],"iteration":473,"passed_time":1679.320159,"remaining_time":1863.549374},
{"learn":[1.446124007],"iteration":474,"passed_time":1682.029082,"remaining_time":1859.084775},
{"learn":[1.445460042],"iteration":475,"passed_time":1685.359882,"remaining_time":1855.312139},
{"learn":[1.445151023],"iteration":476,"passed_time":1689.042636,"remaining_time":1851.927251},
{"learn":[1.444443278],"iteration":477,"passed_time":1692.245409,"remaining_time":1848.016953},
{"learn":[1.443969367],"iteration":478,"passed_time":1695.039871,"remaining_time":1843.665496},
{"learn":[1.442996889],"iteration":479,"passed_time":1697.875114,"remaining_time":1839.364707},
{"learn":[1.442386664],"iteration":480,"passed_time":1700.824526,"remaining_time":1835.1932},
{"learn":[1.441734801],"iteration":481,"passed_time":1704.298037,"remaining_time":1831.590007},
{"learn":[1.440551843],"iteration":482,"passed_time":1707.433502,"remaining_time":1827.625509},
{"learn":[1.439751184],"iteration":483,"passed_time":1710.45219,"remaining_time":1823.539938},
{"learn":[1.439077809],"iteration":484,"passed_time":1713.195672,"remaining_time":1819.166539},
{"learn":[1.438528563],"iteration":485,"passed_time":1715.992195,"remaining_time":1814.855943},
{"learn":[1.437917228],"iteration":486,"passed_time":1719.488712,"remaining_time":1811.288931},
{"learn":[1.437258852],"iteration":487,"passed_time":1723.006127,"remaining_time":1807.744133},
{"learn":[1.436346254],"iteration":488,"passed_time":1727.455374,"remaining_time":1805.173203},
{"learn":[1.435908933],"iteration":489,"passed_time":1732.02064,"remaining_time":1802.71536},
{"learn":[1.435424989],"iteration":490,"passed_time":1736.469344,"remaining_time":1800.128098},
{"learn":[1.434552514],"iteration":491,"passed_time":1740.731901,"remaining_time":1797.341069},
{"learn":[1.433538415],"iteration":492,"passed_time":1744.558608,"remaining_time":1794.099826},
{"learn":[1.432987448],"iteration":493,"passed_time":1749.181565,"remaining_time":1791.671805},
{"learn":[1.431742856],"iteration":494,"passed_time":1754.357426,"remaining_time":1789.79899},
{"learn":[1.430801689],"iteration":495,"passed_time":1759.031537,"remaining_time":1787.403013},
{"learn":[1.429821145],"iteration":496,"passed_time":1763.048252,"remaining_time":1784.332537},
{"learn":[1.42909115],"iteration":497,"passed_time":1766.578456,"remaining_time":1780.767841},
{"learn":[1.428078702],"iteration":498,"passed_time":1770.017305,"remaining_time":1777.111563},
{"learn":[1.427628224],"iteration":499,"passed_time":1773.33552,"remaining_time":1773.33552},
{"learn":[1.426502314],"iteration":500,"passed_time":1776.754657,"remaining_time":1769.661824},
{"learn":[1.425531136],"iteration":501,"passed_time":1781.17173,"remaining_time":1766.979127},
{"learn":[1.42472625],"iteration":502,"passed_time":1785.089555,"remaining_time":1763.796241},
{"learn":[1.424177604],"iteration":503,"passed_time":1788.873008,"remaining_time":1760.478198},
{"learn":[1.423526312],"iteration":504,"passed_time":1792.326881,"remaining_time":1756.835259},
{"learn":[1.422958435],"iteration":505,"passed_time":1795.912781,"remaining_time":1753.321964},
{"learn":[1.422563924],"iteration":506,"passed_time":1799.702029,"remaining_time":1750.006115},
{"learn":[1.422036009],"iteration":507,"passed_time":1803.977017,"remaining_time":1747.158844},
{"learn":[1.420914476],"iteration":508,"passed_time":1808.073547,"remaining_time":1744.133814},
{"learn":[1.420271645],"iteration":509,"passed_time":1812.242681,"remaining_time":1741.17434},
{"learn":[1.419646143],"iteration":510,"passed_time":1817.306181,"remaining_time":1739.065993},
{"learn":[1.418916397],"iteration":511,"passed_time":1822.008996,"remaining_time":1736.602325},
{"learn":[1.418473554],"iteration":512,"passed_time":1825.768886,"remaining_time":1733.234791},
{"learn":[1.417623493],"iteration":513,"passed_time":1829.469816,"remaining_time":1729.809982},
{"learn":[1.417141853],"iteration":514,"passed_time":1833.107112,"remaining_time":1726.324173},
{"learn":[1.416267702],"iteration":515,"passed_time":1836.600899,"remaining_time":1722.703168},
{"learn":[1.41571093],"iteration":516,"passed_time":1840.117258,"remaining_time":1719.103744},
{"learn":[1.41484282],"iteration":517,"passed_time":1843.579173,"remaining_time":1715.453979},
{"learn":[1.413870156],"iteration":518,"passed_time":1847.21227,"remaining_time":1711.963588},
{"learn":[1.412626887],"iteration":519,"passed_time":1850.89123,"remaining_time":1708.514982},
{"learn":[1.412246447],"iteration":520,"passed_time":1854.53132,"remaining_time":1705.029755},
{"learn":[1.411321115],"iteration":521,"passed_time":1858.066621,"remaining_time":1701.447979},
{"learn":[1.41045472],"iteration":522,"passed_time":1861.469997,"remaining_time":1697.746059},
{"learn":[1.40958225],"iteration":523,"passed_time":1864.989919,"remaining_time":1694.151147},
{"learn":[1.408604224],"iteration":524,"passed_time":1868.399244,"remaining_time":1690.456459},
{"learn":[1.407303703],"iteration":525,"passed_time":1871.859321,"remaining_time":1686.80859},
{"learn":[1.406628749],"iteration":526,"passed_time":1875.361276,"remaining_time":1683.19902},
{"learn":[1.405597174],"iteration":527,"passed_time":1878.894213,"remaining_time":1679.617554},
{"learn":[1.405010991],"iteration":528,"passed_time":1882.430156,"remaining_time":1676.038948},
{"learn":[1.404388228],"iteration":529,"passed_time":1885.967651,"remaining_time":1672.461879},
{"learn":[1.403585521],"iteration":530,"passed_time":1890.654946,"remaining_time":1669.900508},
{"learn":[1.402976724],"iteration":531,"passed_time":1894.617082,"remaining_time":1666.693223},
{"learn":[1.402098173],"iteration":532,"passed_time":1899.59165,"remaining_time":1664.37017},
{"learn":[1.40152795],"iteration":533,"passed_time":1904.012267,"remaining_time":1661.553776},
{"learn":[1.401224242],"iteration":534,"passed_time":1907.600924,"remaining_time":1658.00828},
{"learn":[1.400503862],"iteration":535,"passed_time":1911.736671,"remaining_time":1654.936223},
{"learn":[1.3994562],"iteration":536,"passed_time":1915.611683,"remaining_time":1651.635399},
{"learn":[1.398675019],"iteration":537,"passed_time":1919.127872,"remaining_time":1648.024306},
{"learn":[1.398009824],"iteration":538,"passed_time":1922.532309,"remaining_time":1644.317986},
{"learn":[1.396921986],"iteration":539,"passed_time":1925.814731,"remaining_time":1640.508845},
{"learn":[1.395997722],"iteration":540,"passed_time":1929.053424,"remaining_time":1636.66455},
{"learn":[1.395474058],"iteration":541,"passed_time":1932.482595,"remaining_time":1632.983448},
{"learn":[1.394922436],"iteration":542,"passed_time":1936.0766,"remaining_time":1629.442},
{"learn":[1.393969581],"iteration":543,"passed_time":1939.513158,"remaining_time":1625.768383},
{"learn":[1.393562678],"iteration":544,"passed_time":1942.820233,"remaining_time":1621.987534},
{"learn":[1.392783735],"iteration":545,"passed_time":1946.13537,"remaining_time":1618.215124},
{"learn":[1.391581585],"iteration":546,"passed_time":1949.30826,"remaining_time":1614.326585},
{"learn":[1.391174795],"iteration":547,"passed_time":1952.468375,"remaining_time":1610.430119},
{"learn":[1.390474536],"iteration":548,"passed_time":1955.76159,"remaining_time":1606.645678},
{"learn":[1.389557357],"iteration":549,"passed_time":1959.111854,"remaining_time":1602.909699},
{"learn":[1.388959715],"iteration":550,"passed_time":1962.418109,"remaining_time":1599.139258},
{"learn":[1.38819913],"iteration":551,"passed_time":1965.742821,"remaining_time":1595.385478},
{"learn":[1.387356368],"iteration":552,"passed_time":1969.536196,"remaining_time":1592.012079},
{"learn":[1.386556258],"iteration":553,"passed_time":1972.970932,"remaining_time":1588.34844},
{"learn":[1.3861744],"iteration":554,"passed_time":1977.371963,"remaining_time":1585.460403},
{"learn":[1.385452786],"iteration":555,"passed_time":1982.771387,"remaining_time":1583.364201},
{"learn":[1.38466985],"iteration":556,"passed_time":1986.580042,"remaining_time":1579.990949},
{"learn":[1.383827467],"iteration":557,"passed_time":1989.736319,"remaining_time":1576.099378},
{"learn":[1.382881821],"iteration":558,"passed_time":1992.756364,"remaining_time":1572.102963},
{"learn":[1.382151954],"iteration":559,"passed_time":1996.18312,"remaining_time":1568.429594},
{"learn":[1.381477861],"iteration":560,"passed_time":1999.2596,"remaining_time":1564.483003},
{"learn":[1.380952039],"iteration":561,"passed_time":2002.478934,"remaining_time":1560.650842},
{"learn":[1.380330646],"iteration":562,"passed_time":2005.281085,"remaining_time":1556.497041},
{"learn":[1.379840958],"iteration":563,"passed_time":2008.099066,"remaining_time":1552.360271},
{"learn":[1.379293309],"iteration":564,"passed_time":2011.015053,"remaining_time":1548.303625},
{"learn":[1.378789767],"iteration":565,"passed_time":2013.89123,"remaining_time":1544.220484},
{"learn":[1.378396139],"iteration":566,"passed_time":2016.720629,"remaining_time":1540.105877},
{"learn":[1.37786507],"iteration":567,"passed_time":2019.507999,"remaining_time":1535.96383},
{"learn":[1.377416138],"iteration":568,"passed_time":2022.387118,"remaining_time":1531.896042},
{"learn":[1.376523397],"iteration":569,"passed_time":2025.219716,"remaining_time":1527.79733},
{"learn":[1.375536041],"iteration":570,"passed_time":2027.992455,"remaining_time":1523.658079},
{"learn":[1.374840549],"iteration":571,"passed_time":2030.842858,"remaining_time":1519.581719},
{"learn":[1.374547676],"iteration":572,"passed_time":2033.655396,"remaining_time":1515.481421},
{"learn":[1.373990983],"iteration":573,"passed_time":2037.502966,"remaining_time":1512.153769},
{"learn":[1.373361904],"iteration":574,"passed_time":2041.025652,"remaining_time":1508.584178},
{"learn":[1.37266295],"iteration":575,"passed_time":2045.149324,"remaining_time":1505.457141},
{"learn":[1.371621264],"iteration":576,"passed_time":2048.304939,"remaining_time":1501.616966},
{"learn":[1.370956851],"iteration":577,"passed_time":2051.198773,"remaining_time":1497.588032},
{"learn":[1.370228717],"iteration":578,"passed_time":2053.978135,"remaining_time":1493.479784},
{"learn":[1.36925904],"iteration":579,"passed_time":2056.761978,"remaining_time":1489.379363},
{"learn":[1.368453802],"iteration":580,"passed_time":2059.583287,"remaining_time":1485.310495},
{"learn":[1.367836687],"iteration":581,"passed_time":2062.423636,"remaining_time":1481.259587},
{"learn":[1.366986141],"iteration":582,"passed_time":2065.190288,"remaining_time":1477.160121},
{"learn":[1.366242571],"iteration":583,"passed_time":2068.023153,"remaining_time":1473.112383},
{"learn":[1.365460131],"iteration":584,"passed_time":2070.89438,"remaining_time":1469.096013},
{"learn":[1.364818335],"iteration":585,"passed_time":2073.6634,"remaining_time":1465.011344},
{"learn":[1.364334035],"iteration":586,"passed_time":2076.455798,"remaining_time":1460.947606},
{"learn":[1.363713788],"iteration":587,"passed_time":2079.237216,"remaining_time":1456.880498},
{"learn":[1.363132521],"iteration":588,"passed_time":2082.118098,"remaining_time":1452.887162},
{"learn":[1.362703869],"iteration":589,"passed_time":2084.889233,"remaining_time":1448.821332},
{"learn":[1.362228624],"iteration":590,"passed_time":2087.574613,"remaining_time":1444.700536},
{"learn":[1.361151692],"iteration":591,"passed_time":2090.53683,"remaining_time":1440.775383},
{"learn":[1.360520343],"iteration":592,"passed_time":2093.428763,"remaining_time":1436.805239},
{"learn":[1.359608831],"iteration":593,"passed_time":2096.26078,"remaining_time":1432.797772},
{"learn":[1.358818759],"iteration":594,"passed_time":2099.095607,"remaining_time":1428.79617},
{"learn":[1.358290799],"iteration":595,"passed_time":2101.815297,"remaining_time":1424.720436},
{"learn":[1.357581958],"iteration":596,"passed_time":2104.641204,"remaining_time":1420.720947},
{"learn":[1.356957227],"iteration":597,"passed_time":2107.36891,"remaining_time":1416.659368},
{"learn":[1.356396674],"iteration":598,"passed_time":2110.187624,"remaining_time":1412.663167},
{"learn":[1.355450138],"iteration":599,"passed_time":2113.09682,"remaining_time":1408.731213},
{"learn":[1.354916226],"iteration":600,"passed_time":2115.955994,"remaining_time":1404.769453},
{"learn":[1.354310626],"iteration":601,"passed_time":2118.892749,"remaining_time":1400.862648},
{"learn":[1.353553741],"iteration":602,"passed_time":2121.587842,"remaining_time":1396.799956},
{"learn":[1.353251214],"iteration":603,"passed_time":2124.406732,"remaining_time":1392.822956},
{"learn":[1.352452338],"iteration":604,"passed_time":2127.294319,"remaining_time":1388.894638},
{"learn":[1.351947959],"iteration":605,"passed_time":2130.100684,"remaining_time":1384.916946},
{"learn":[1.35127763],"iteration":606,"passed_time":2132.831911,"remaining_time":1380.894466},
{"learn":[1.350314398],"iteration":607,"passed_time":2135.519345,"remaining_time":1376.847999},
{"learn":[1.349360615],"iteration":608,"passed_time":2138.360014,"remaining_time":1372.904377},
{"learn":[1.348312371],"iteration":609,"passed_time":2141.065881,"remaining_time":1368.878186},
{"learn":[1.347420206],"iteration":610,"passed_time":2143.781197,"remaining_time":1364.862333},
{"learn":[1.34686224],"iteration":611,"passed_time":2146.538077,"remaining_time":1360.877081},
{"learn":[1.346509585],"iteration":612,"passed_time":2149.294038,"remaining_time":1356.895257},
{"learn":[1.345167134],"iteration":613,"passed_time":2152.106142,"remaining_time":1352.952721},
{"learn":[1.344571967],"iteration":614,"passed_time":2154.98322,"remaining_time":1349.054536},
{"learn":[1.34366655],"iteration":615,"passed_time":2157.85046,"remaining_time":1345.153534},
{"learn":[1.342876056],"iteration":616,"passed_time":2160.614361,"remaining_time":1341.191734},
{"learn":[1.342382063],"iteration":617,"passed_time":2163.526307,"remaining_time":1337.325322},
{"learn":[1.34198607],"iteration":618,"passed_time":2166.56578,"remaining_time":1333.540488},
{"learn":[1.341705836],"iteration":619,"passed_time":2169.338152,"remaining_time":1329.594351},
{"learn":[1.341356042],"iteration":620,"passed_time":2172.163782,"remaining_time":1325.684498},
{"learn":[1.340622912],"iteration":621,"passed_time":2175.016643,"remaining_time":1321.79468},
{"learn":[1.340095664],"iteration":622,"passed_time":2177.935678,"remaining_time":1317.948235},
{"learn":[1.339474389],"iteration":623,"passed_time":2180.719232,"remaining_time":1314.023127},
{"learn":[1.33874573],"iteration":624,"passed_time":2183.396803,"remaining_time":1310.038082},
{"learn":[1.338235016],"iteration":625,"passed_time":2186.352334,"remaining_time":1306.223279},
{"learn":[1.33743747],"iteration":626,"passed_time":2189.139513,"remaining_time":1302.311066},
{"learn":[1.336846794],"iteration":627,"passed_time":2192.043836,"remaining_time":1298.471826},
{"learn":[1.33599884],"iteration":628,"passed_time":2194.810043,"remaining_time":1294.554095},
{"learn":[1.335466044],"iteration":629,"passed_time":2197.736289,"remaining_time":1290.734011},
{"learn":[1.334927637],"iteration":630,"passed_time":2200.4415,"remaining_time":1286.787501},
{"learn":[1.334254171],"iteration":631,"passed_time":2203.20936,"remaining_time":1282.8814},
{"learn":[1.333658639],"iteration":632,"passed_time":2205.969379,"remaining_time":1278.974348},
{"learn":[1.332976725],"iteration":633,"passed_time":2209.506794,"remaining_time":1275.519695},
{"learn":[1.332136874],"iteration":634,"passed_time":2212.803484,"remaining_time":1271.926412},
{"learn":[1.331762622],"iteration":635,"passed_time":2215.807493,"remaining_time":1268.166552},
{"learn":[1.330864722],"iteration":636,"passed_time":2218.72418,"remaining_time":1264.359305},
{"learn":[1.33041222],"iteration":637,"passed_time":2221.444747,"remaining_time":1260.443571},
{"learn":[1.330007444],"iteration":638,"passed_time":2224.327914,"remaining_time":1256.623438},
{"learn":[1.329335214],"iteration":639,"passed_time":2227.084997,"remaining_time":1252.735311},
{"learn":[1.329032797],"iteration":640,"passed_time":2229.89201,"remaining_time":1248.878676},
{"learn":[1.328445243],"iteration":641,"passed_time":2232.760076,"remaining_time":1245.059357},
{"learn":[1.327849923],"iteration":642,"passed_time":2235.477901,"remaining_time":1241.159581},
{"learn":[1.327443593],"iteration":643,"passed_time":2238.234322,"remaining_time":1237.284811},
{"learn":[1.327005238],"iteration":644,"passed_time":2240.834592,"remaining_time":1233.327566},
{"learn":[1.326628344],"iteration":645,"passed_time":2243.683487,"remaining_time":1229.510765},
{"learn":[1.326082117],"iteration":646,"passed_time":2246.47197,"remaining_time":1225.663996},
{"learn":[1.325279745],"iteration":647,"passed_time":2249.226904,"remaining_time":1221.802269},
{"learn":[1.324800267],"iteration":648,"passed_time":2251.959762,"remaining_time":1217.932013},
{"learn":[1.324132168],"iteration":649,"passed_time":2254.716695,"remaining_time":1214.07822},
{"learn":[1.323477614],"iteration":650,"passed_time":2257.534524,"remaining_time":1210.260444},
{"learn":[1.322741264],"iteration":651,"passed_time":2260.331831,"remaining_time":1206.434781},
{"learn":[1.322441398],"iteration":652,"passed_time":2263.036883,"remaining_time":1202.563244},
{"learn":[1.321800005],"iteration":653,"passed_time":2265.934042,"remaining_time":1198.796909},
{"learn":[1.321157966],"iteration":654,"passed_time":2268.722938,"remaining_time":1194.976204},
{"learn":[1.320764485],"iteration":655,"passed_time":2271.516476,"remaining_time":1191.161079},
{"learn":[1.320254964],"iteration":656,"passed_time":2274.31561,"remaining_time":1187.351985},
{"learn":[1.319575723],"iteration":657,"passed_time":2277.074756,"remaining_time":1183.525177},
{"learn":[1.318899207],"iteration":658,"passed_time":2279.692689,"remaining_time":1179.628539},
{"learn":[1.318330784],"iteration":659,"passed_time":2282.468762,"remaining_time":1175.817241},
{"learn":[1.317629264],"iteration":660,"passed_time":2285.19411,"remaining_time":1171.983061},
{"learn":[1.317167948],"iteration":661,"passed_time":2288.113502,"remaining_time":1168.251304},
{"learn":[1.316493745],"iteration":662,"passed_time":2290.884307,"remaining_time":1164.446473},
{"learn":[1.31586225],"iteration":663,"passed_time":2293.73211,"remaining_time":1160.683718},
{"learn":[1.315313915],"iteration":664,"passed_time":2296.444473,"remaining_time":1156.855486},
{"learn":[1.314887263],"iteration":665,"passed_time":2299.252879,"remaining_time":1153.078771},
{"learn":[1.314299251],"iteration":666,"passed_time":2302.063044,"remaining_time":1149.305838},
{"learn":[1.31326744],"iteration":667,"passed_time":2304.864429,"remaining_time":1145.531423},
{"learn":[1.31282788],"iteration":668,"passed_time":2307.513214,"remaining_time":1141.684415},
{"learn":[1.312244391],"iteration":669,"passed_time":2310.444138,"remaining_time":1137.979949},
{"learn":[1.311710667],"iteration":670,"passed_time":2313.15758,"remaining_time":1134.171153},
{"learn":[1.311215498],"iteration":671,"passed_time":2315.89546,"remaining_time":1130.377546},
{"learn":[1.310115699],"iteration":672,"passed_time":2318.81571,"remaining_time":1126.675687},
{"learn":[1.309358565],"iteration":673,"passed_time":2321.691578,"remaining_time":1122.95468},
{"learn":[1.308845511],"iteration":674,"passed_time":2324.577558,"remaining_time":1119.241046},
{"learn":[1.308219743],"iteration":675,"passed_time":2327.359326,"remaining_time":1115.479914},
{"learn":[1.307683657],"iteration":676,"passed_time":2330.049703,"remaining_time":1111.678071},
{"learn":[1.307249777],"iteration":677,"passed_time":2332.779521,"remaining_time":1107.898239},
{"learn":[1.306500899],"iteration":678,"passed_time":2335.471997,"remaining_time":1104.103845},
{"learn":[1.30601404],"iteration":679,"passed_time":2338.341744,"remaining_time":1100.396115},
{"learn":[1.305551828],"iteration":680,"passed_time":2341.119075,"remaining_time":1096.647555},
{"learn":[1.304865745],"iteration":681,"passed_time":2343.836063,"remaining_time":1092.873707},
{"learn":[1.304478269],"iteration":682,"passed_time":2346.57504,"remaining_time":1089.113159},
{"learn":[1.303895336],"iteration":683,"passed_time":2349.589568,"remaining_time":1085.4829},
{"learn":[1.303286086],"iteration":684,"passed_time":2352.382882,"remaining_time":1081.752712},
{"learn":[1.302761038],"iteration":685,"passed_time":2355.136836,"remaining_time":1078.00724},
{"learn":[1.302220417],"iteration":686,"passed_time":2357.965966,"remaining_time":1074.298904},
{"learn":[1.301574762],"iteration":687,"passed_time":2360.672732,"remaining_time":1070.537634},
{"learn":[1.300695113],"iteration":688,"passed_time":2363.438012,"remaining_time":1066.805837},
{"learn":[1.299849819],"iteration":689,"passed_time":2366.311607,"remaining_time":1063.125504},
{"learn":[1.299235088],"iteration":690,"passed_time":2369.065664,"remaining_time":1059.394052},
{"learn":[1.298441205],"iteration":691,"passed_time":2371.709475,"remaining_time":1055.616356},
{"learn":[1.297833228],"iteration":692,"passed_time":2374.47186,"remaining_time":1051.89446},
{"learn":[1.297324474],"iteration":693,"passed_time":2377.297956,"remaining_time":1048.203422},
{"learn":[1.296520118],"iteration":694,"passed_time":2380.192288,"remaining_time":1044.544817},
{"learn":[1.296023756],"iteration":695,"passed_time":2382.923176,"remaining_time":1040.817019},
{"learn":[1.29545765],"iteration":696,"passed_time":2385.67866,"remaining_time":1037.102775},
{"learn":[1.294807864],"iteration":697,"passed_time":2388.495706,"remaining_time":1033.417913},
{"learn":[1.294087112],"iteration":698,"passed_time":2391.457939,"remaining_time":1029.798054},
{"learn":[1.293464629],"iteration":699,"passed_time":2394.553088,"remaining_time":1026.237038},
{"learn":[1.292809427],"iteration":700,"passed_time":2397.375388,"remaining_time":1022.560971},
{"learn":[1.292415156],"iteration":701,"passed_time":2400.030579,"remaining_time":1018.8164},
{"learn":[1.291788344],"iteration":702,"passed_time":2402.691245,"remaining_time":1015.07724},
{"learn":[1.291210931],"iteration":703,"passed_time":2405.350358,"remaining_time":1011.340492},
{"learn":[1.290601885],"iteration":704,"passed_time":2408.171613,"remaining_time":1007.674647},
{"learn":[1.290035254],"iteration":705,"passed_time":2410.993944,"remaining_time":1004.011642},
{"learn":[1.289450869],"iteration":706,"passed_time":2413.830685,"remaining_time":1000.356988},
{"learn":[1.288606154],"iteration":707,"passed_time":2416.599636,"remaining_time":996.676686},
{"learn":[1.287941191],"iteration":708,"passed_time":2419.441968,"remaining_time":993.0290729},
{"learn":[1.287665479],"iteration":709,"passed_time":2422.219879,"remaining_time":989.3574154},
{"learn":[1.287088962],"iteration":710,"passed_time":2425.032688,"remaining_time":985.7024569},
{"learn":[1.286589121],"iteration":711,"passed_time":2427.739997,"remaining_time":982.0071897},
{"learn":[1.286179668],"iteration":712,"passed_time":2430.469285,"remaining_time":978.3235409},
{"learn":[1.285301563],"iteration":713,"passed_time":2433.205042,"remaining_time":974.6451568},
{"learn":[1.284644261],"iteration":714,"passed_time":2435.955679,"remaining_time":970.9753404},
{"learn":[1.283578317],"iteration":715,"passed_time":2438.791544,"remaining_time":967.3418973},
{"learn":[1.283315475],"iteration":716,"passed_time":2441.549931,"remaining_time":963.6800982},
{"learn":[1.282453825],"iteration":717,"passed_time":2444.327853,"remaining_time":960.0284881},
{"learn":[1.28156644],"iteration":718,"passed_time":2447.089853,"remaining_time":956.373086},
{"learn":[1.281254877],"iteration":719,"passed_time":2449.879414,"remaining_time":952.7308833},
{"learn":[1.280528942],"iteration":720,"passed_time":2452.502991,"remaining_time":949.0268161},
{"learn":[1.279566256],"iteration":721,"passed_time":2455.070889,"remaining_time":945.3043036},
{"learn":[1.278981745],"iteration":722,"passed_time":2458.16651,"remaining_time":941.7871692},
{"learn":[1.278434991],"iteration":723,"passed_time":2461.146409,"remaining_time":938.227084},
{"learn":[1.277666813],"iteration":724,"passed_time":2463.865922,"remaining_time":934.5698323},
{"learn":[1.277248667],"iteration":725,"passed_time":2466.645081,"remaining_time":930.937675},
{"learn":[1.276600978],"iteration":726,"passed_time":2469.528977,"remaining_time":927.3471949},
{"learn":[1.275947952],"iteration":727,"passed_time":2472.452241,"remaining_time":923.7733648},
{"learn":[1.27514487],"iteration":728,"passed_time":2475.230001,"remaining_time":920.1472295},
{"learn":[1.274331071],"iteration":729,"passed_time":2478.043915,"remaining_time":916.5367906},
{"learn":[1.273586964],"iteration":730,"passed_time":2480.976864,"remaining_time":912.9723344},
{"learn":[1.273128792],"iteration":731,"passed_time":2483.975483,"remaining_time":909.4336467},
{"learn":[1.272415597],"iteration":732,"passed_time":2486.805001,"remaining_time":905.8348366},
{"learn":[1.271958785],"iteration":733,"passed_time":2489.672806,"remaining_time":902.2519976},
{"learn":[1.271452946],"iteration":734,"passed_time":2492.462914,"remaining_time":898.6430915},
{"learn":[1.270993397],"iteration":735,"passed_time":2495.224937,"remaining_time":895.0263362},
{"learn":[1.270457404],"iteration":736,"passed_time":2498.062927,"remaining_time":891.4390093},
{"learn":[1.269670844],"iteration":737,"passed_time":2500.78995,"remaining_time":887.8143182},
{"learn":[1.269155911],"iteration":738,"passed_time":2503.62427,"remaining_time":884.2299519},
{"learn":[1.268469285],"iteration":739,"passed_time":2506.496461,"remaining_time":880.6609186},
{"learn":[1.26784319],"iteration":740,"passed_time":2509.249974,"remaining_time":877.052285},
{"learn":[1.267583712],"iteration":741,"passed_time":2512.012631,"remaining_time":873.4491357},
{"learn":[1.267224947],"iteration":742,"passed_time":2514.710307,"remaining_time":869.8257725},
{"learn":[1.266625302],"iteration":743,"passed_time":2517.489192,"remaining_time":866.2328402},
{"learn":[1.265963601],"iteration":744,"passed_time":2520.272153,"remaining_time":862.6434887},
{"learn":[1.265668824],"iteration":745,"passed_time":2522.992955,"remaining_time":859.0351348},
{"learn":[1.265266862],"iteration":746,"passed_time":2525.819912,"remaining_time":855.4651108},
{"learn":[1.264562409],"iteration":747,"passed_time":2528.684629,"remaining_time":851.9097947},
{"learn":[1.263878611],"iteration":748,"passed_time":2531.480091,"remaining_time":848.3331145},
{"learn":[1.263132433],"iteration":749,"passed_time":2534.363347,"remaining_time":844.7877824},
{"learn":[1.262671015],"iteration":750,"passed_time":2537.158449,"remaining_time":841.2149851},
{"learn":[1.262192107],"iteration":751,"passed_time":2540.005024,"remaining_time":837.6612314},
{"learn":[1.261604575],"iteration":752,"passed_time":2542.740708,"remaining_time":834.0729814},
{"learn":[1.26082323],"iteration":753,"passed_time":2545.513445,"remaining_time":830.4990814},
{"learn":[1.260207681],"iteration":754,"passed_time":2548.296364,"remaining_time":826.9306082},
{"learn":[1.259764946],"iteration":755,"passed_time":2551.064886,"remaining_time":823.3595663},
{"learn":[1.259075941],"iteration":756,"passed_time":2553.880577,"remaining_time":819.8057863},
{"learn":[1.258491063],"iteration":757,"passed_time":2556.490754,"remaining_time":816.188341},
{"learn":[1.257957983],"iteration":758,"passed_time":2559.200801,"remaining_time":812.6052608},
{"learn":[1.257612382],"iteration":759,"passed_time":2561.975612,"remaining_time":809.0449301},
{"learn":[1.257064187],"iteration":760,"passed_time":2564.711953,"remaining_time":805.4745819},
{"learn":[1.256319181],"iteration":761,"passed_time":2567.452804,"remaining_time":801.907831},
{"learn":[1.255540783],"iteration":762,"passed_time":2570.158783,"remaining_time":798.3324137},
{"learn":[1.255130306],"iteration":763,"passed_time":2572.737816,"remaining_time":794.7200584},
{"learn":[1.254690709],"iteration":764,"passed_time":2575.560787,"remaining_time":791.1853397},
{"learn":[1.254020389],"iteration":765,"passed_time":2578.36427,"remaining_time":787.6465264},
{"learn":[1.253610995],"iteration":766,"passed_time":2581.149422,"remaining_time":784.1040616},
{"learn":[1.253276032],"iteration":767,"passed_time":2584.018303,"remaining_time":780.5888624},
{"learn":[1.252546849],"iteration":768,"passed_time":2586.853381,"remaining_time":777.0651899},
{"learn":[1.252177159],"iteration":769,"passed_time":2589.636047,"remaining_time":773.5276503},
{"learn":[1.251841774],"iteration":770,"passed_time":2592.359243,"remaining_time":769.9744055},
{"learn":[1.251342014],"iteration":771,"passed_time":2595.140717,"remaining_time":766.4405226},
{"learn":[1.250462666],"iteration":772,"passed_time":2597.992584,"remaining_time":762.9292582},
{"learn":[1.249778361],"iteration":773,"passed_time":2600.725299,"remaining_time":759.3849065},
{"learn":[1.249045503],"iteration":774,"passed_time":2603.941623,"remaining_time":755.9830519},
{"learn":[1.248626518],"iteration":775,"passed_time":2607.036051,"remaining_time":752.5464888},
{"learn":[1.248163586],"iteration":776,"passed_time":2610.257766,"remaining_time":749.1473382},
{"learn":[1.247846951],"iteration":777,"passed_time":2613.450132,"remaining_time":745.7402691},
{"learn":[1.247028723],"iteration":778,"passed_time":2616.587141,"remaining_time":742.3180463},
{"learn":[1.246509731],"iteration":779,"passed_time":2619.578193,"remaining_time":738.8553879},
{"learn":[1.245780983],"iteration":780,"passed_time":2622.549162,"remaining_time":735.3883054},
{"learn":[1.24542648],"iteration":781,"passed_time":2625.664559,"remaining_time":731.9627544},
{"learn":[1.244972722],"iteration":782,"passed_time":2628.615808,"remaining_time":728.4925035},
{"learn":[1.244558296],"iteration":783,"passed_time":2631.418354,"remaining_time":724.9826078},
{"learn":[1.24428617],"iteration":784,"passed_time":2634.365058,"remaining_time":721.5139968},
{"learn":[1.243611672],"iteration":785,"passed_time":2637.163112,"remaining_time":718.0062416},
{"learn":[1.24317936],"iteration":786,"passed_time":2639.947384,"remaining_time":714.49656},
{"learn":[1.242788133],"iteration":787,"passed_time":2643.670717,"remaining_time":711.2413603},
{"learn":[1.242168602],"iteration":788,"passed_time":2647.327446,"remaining_time":707.9671623},
{"learn":[1.241825727],"iteration":789,"passed_time":2651.260856,"remaining_time":704.765544},
{"learn":[1.240973176],"iteration":790,"passed_time":2654.250781,"remaining_time":701.3127853},
{"learn":[1.240760078],"iteration":791,"passed_time":2657.181068,"remaining_time":697.8455329},
{"learn":[1.240432796],"iteration":792,"passed_time":2659.942932,"remaining_time":694.3356708},
{"learn":[1.239831931],"iteration":793,"passed_time":2662.667125,"remaining_time":690.8179191},
{"learn":[1.239564775],"iteration":794,"passed_time":2665.544755,"remaining_time":687.3417294},
{"learn":[1.238932931],"iteration":795,"passed_time":2668.387376,"remaining_time":683.8580713},
{"learn":[1.238530713],"iteration":796,"passed_time":2671.236021,"remaining_time":680.3775561},
{"learn":[1.237903858],"iteration":797,"passed_time":2673.926282,"remaining_time":676.8585325},
{"learn":[1.237518626],"iteration":798,"passed_time":2676.734855,"remaining_time":673.3713464},
{"learn":[1.237042486],"iteration":799,"passed_time":2679.617801,"remaining_time":669.9044502},
{"learn":[1.236572599],"iteration":800,"passed_time":2682.449218,"remaining_time":666.4262102},
{"learn":[1.235691987],"iteration":801,"passed_time":2685.259113,"remaining_time":662.9442698},
{"learn":[1.235164531],"iteration":802,"passed_time":2688.083415,"remaining_time":659.4675376},
{"learn":[1.23490837],"iteration":803,"passed_time":2690.836122,"remaining_time":655.9749751},
{"learn":[1.234431265],"iteration":804,"passed_time":2693.636589,"remaining_time":652.4958197},
{"learn":[1.23389166],"iteration":805,"passed_time":2696.319695,"remaining_time":648.9901004},
{"learn":[1.2334528],"iteration":806,"passed_time":2699.089424,"remaining_time":645.5071362},
{"learn":[1.232638388],"iteration":807,"passed_time":2702.047549,"remaining_time":642.0707048},
{"learn":[1.232324257],"iteration":808,"passed_time":2704.787757,"remaining_time":638.584007},
{"learn":[1.231852349],"iteration":809,"passed_time":2707.546433,"remaining_time":635.1034843},
{"learn":[1.231287545],"iteration":810,"passed_time":2710.285445,"remaining_time":631.6201592},
{"learn":[1.230797131],"iteration":811,"passed_time":2713.096551,"remaining_time":628.1553592},
{"learn":[1.229992745],"iteration":812,"passed_time":2715.965195,"remaining_time":624.7054016},
{"learn":[1.229450806],"iteration":813,"passed_time":2718.723671,"remaining_time":621.2316987},
{"learn":[1.228749674],"iteration":814,"passed_time":2721.550391,"remaining_time":617.7752422},
{"learn":[1.227986543],"iteration":815,"passed_time":2724.426652,"remaining_time":614.3315},
{"learn":[1.227427473],"iteration":816,"passed_time":2727.241813,"remaining_time":610.8754611},
{"learn":[1.227123228],"iteration":817,"passed_time":2730.034985,"remaining_time":607.4160969},
{"learn":[1.226716971],"iteration":818,"passed_time":2732.78474,"remaining_time":603.9487642},
{"learn":[1.226255293],"iteration":819,"passed_time":2735.507787,"remaining_time":600.4773192},
{"learn":[1.225762373],"iteration":820,"passed_time":2738.300497,"remaining_time":597.0228854},
{"learn":[1.225001697],"iteration":821,"passed_time":2741.107902,"remaining_time":593.5732439},
{"learn":[1.224410398],"iteration":822,"passed_time":2743.981796,"remaining_time":590.1394628},
{"learn":[1.223875884],"iteration":823,"passed_time":2746.67442,"remaining_time":586.6683227},
{"learn":[1.223459024],"iteration":824,"passed_time":2749.425158,"remaining_time":583.2113972},
{"learn":[1.222815787],"iteration":825,"passed_time":2752.139478,"remaining_time":579.7485099},
{"learn":[1.222549297],"iteration":826,"passed_time":2754.839882,"remaining_time":576.2845219},
{"learn":[1.222322034],"iteration":827,"passed_time":2757.571086,"remaining_time":572.8287762},
{"learn":[1.221814894],"iteration":828,"passed_time":2760.41789,"remaining_time":569.3986238},
{"learn":[1.221155043],"iteration":829,"passed_time":2763.060162,"remaining_time":565.927985},
{"learn":[1.22081378],"iteration":830,"passed_time":2765.900167,"remaining_time":562.4995527},
{"learn":[1.219920259],"iteration":831,"passed_time":2768.688684,"remaining_time":559.0621382},
{"learn":[1.219363655],"iteration":832,"passed_time":2771.49653,"remaining_time":555.6301567},
{"learn":[1.218758168],"iteration":833,"passed_time":2774.283614,"remaining_time":552.1955395},
{"learn":[1.218001475],"iteration":834,"passed_time":2777.22542,"remaining_time":548.793047},
{"learn":[1.217615361],"iteration":835,"passed_time":2780.153085,"remaining_time":545.3888827},
{"learn":[1.217326331],"iteration":836,"passed_time":2782.982428,"remaining_time":541.9667093},
{"learn":[1.216544137],"iteration":837,"passed_time":2785.832662,"remaining_time":538.5499895},
{"learn":[1.216214986],"iteration":838,"passed_time":2788.652924,"remaining_time":535.1288686},
{"learn":[1.215977262],"iteration":839,"passed_time":2791.458162,"remaining_time":531.7063165},
{"learn":[1.21527191],"iteration":840,"passed_time":2794.3091,"remaining_time":528.2938727},
{"learn":[1.214775979],"iteration":841,"passed_time":2797.069738,"remaining_time":524.8658178},
{"learn":[1.214374939],"iteration":842,"passed_time":2799.872653,"remaining_time":521.4472201},
{"learn":[1.214061792],"iteration":843,"passed_time":2802.573178,"remaining_time":518.0111562},
{"learn":[1.213844145],"iteration":844,"passed_time":2805.433019,"remaining_time":514.6060568},
{"learn":[1.213320332],"iteration":845,"passed_time":2808.155575,"remaining_time":511.177256},
{"learn":[1.212734331],"iteration":846,"passed_time":2810.756838,"remaining_time":507.7282128},
{"learn":[1.212129909],"iteration":847,"passed_time":2813.515083,"remaining_time":504.3093073},
{"learn":[1.211783181],"iteration":848,"passed_time":2816.230995,"remaining_time":500.884429},
{"learn":[1.211116304],"iteration":849,"passed_time":2819.049306,"remaining_time":497.4792892},
{"learn":[1.210820301],"iteration":850,"passed_time":2821.785512,"remaining_time":494.0611531},
{"learn":[1.210156172],"iteration":851,"passed_time":2824.478005,"remaining_time":490.6370243},
{"learn":[1.209393921],"iteration":852,"passed_time":2827.256927,"remaining_time":487.2295057},
{"learn":[1.208675566],"iteration":853,"passed_time":2830.101322,"remaining_time":483.8346523},
{"learn":[1.208315871],"iteration":854,"passed_time":2832.85598,"remaining_time":480.425868},
{"learn":[1.207931836],"iteration":855,"passed_time":2835.633403,"remaining_time":477.0224417},
{"learn":[1.207248508],"iteration":856,"passed_time":2838.531364,"remaining_time":473.6405894},
{"learn":[1.206980302],"iteration":857,"passed_time":2841.292861,"remaining_time":470.23728},
{"learn":[1.206707097],"iteration":858,"passed_time":2844.053146,"remaining_time":466.8352661},
{"learn":[1.206347576],"iteration":859,"passed_time":2846.859442,"remaining_time":463.4422347},
{"learn":[1.205725502],"iteration":860,"passed_time":2849.717676,"remaining_time":460.0589511},
{"learn":[1.205258096],"iteration":861,"passed_time":2852.65729,"remaining_time":456.6899141},
{"learn":[1.204539804],"iteration":862,"passed_time":2855.765564,"remaining_time":453.348647},
{"learn":[1.204049597],"iteration":863,"passed_time":2858.724866,"remaining_time":449.9844696},
{"learn":[1.203736457],"iteration":864,"passed_time":2861.541626,"remaining_time":446.5989822},
{"learn":[1.203519709],"iteration":865,"passed_time":2864.27268,"remaining_time":443.2015464},
{"learn":[1.203018222],"iteration":866,"passed_time":2867.006779,"remaining_time":439.8061149},
{"learn":[1.202428915],"iteration":867,"passed_time":2869.797141,"remaining_time":436.4207633},
{"learn":[1.202093581],"iteration":868,"passed_time":2872.601313,"remaining_time":433.038863},
{"learn":[1.201839255],"iteration":869,"passed_time":2875.248527,"remaining_time":429.6348373},
{"learn":[1.201260456],"iteration":870,"passed_time":2877.861529,"remaining_time":426.2274825},
{"learn":[1.200797216],"iteration":871,"passed_time":2880.623053,"remaining_time":422.8437509},
{"learn":[1.199958963],"iteration":872,"passed_time":2883.486465,"remaining_time":419.4762669},
{"learn":[1.199460093],"iteration":873,"passed_time":2886.54417,"remaining_time":416.1379467},
{"learn":[1.198775905],"iteration":874,"passed_time":2889.673539,"remaining_time":412.8105055},
{"learn":[1.198166976],"iteration":875,"passed_time":2892.765289,"remaining_time":409.4781917},
{"learn":[1.197672716],"iteration":876,"passed_time":2895.946206,"remaining_time":406.158932},
{"learn":[1.19686939],"iteration":877,"passed_time":2899.152854,"remaining_time":402.8435628},
{"learn":[1.196270129],"iteration":878,"passed_time":2902.000407,"remaining_time":399.4790094},
{"learn":[1.195857235],"iteration":879,"passed_time":2904.698942,"remaining_time":396.0953102},
{"learn":[1.195607372],"iteration":880,"passed_time":2907.543761,"remaining_time":392.7329257},
{"learn":[1.195412038],"iteration":881,"passed_time":2910.323138,"remaining_time":389.3629595},
{"learn":[1.19487042],"iteration":882,"passed_time":2913.164435,"remaining_time":386.0025356},
{"learn":[1.194521037],"iteration":883,"passed_time":2915.84206,"remaining_time":382.6218088},
{"learn":[1.193886443],"iteration":884,"passed_time":2918.63924,"remaining_time":379.2582063},
{"learn":[1.19327632],"iteration":885,"passed_time":2921.557266,"remaining_time":375.9114315},
{"learn":[1.192630982],"iteration":886,"passed_time":2924.295273,"remaining_time":372.5426898},
{"learn":[1.192082025],"iteration":887,"passed_time":2927.11305,"remaining_time":369.1854298},
{"learn":[1.191445315],"iteration":888,"passed_time":2929.921816,"remaining_time":365.8282582},
{"learn":[1.19074394],"iteration":889,"passed_time":2932.671589,"remaining_time":362.4650279},
{"learn":[1.19059297],"iteration":890,"passed_time":2935.476098,"remaining_time":359.1098705},
{"learn":[1.190009987],"iteration":891,"passed_time":2938.159738,"remaining_time":355.7413136},
{"learn":[1.189611708],"iteration":892,"passed_time":2941.01458,"remaining_time":352.3948041},
{"learn":[1.189070246],"iteration":893,"passed_time":2943.672768,"remaining_time":349.0260777},
{"learn":[1.188516109],"iteration":894,"passed_time":2946.323437,"remaining_time":345.6580568},
{"learn":[1.188247905],"iteration":895,"passed_time":2949.089451,"remaining_time":342.3050256},
{"learn":[1.187736826],"iteration":896,"passed_time":2951.964171,"remaining_time":338.9657855},
{"learn":[1.187316947],"iteration":897,"passed_time":2954.687958,"remaining_time":335.6104362},
{"learn":[1.18676282],"iteration":898,"passed_time":2957.371861,"remaining_time":332.2520111},
{"learn":[1.186593454],"iteration":899,"passed_time":2960.156915,"remaining_time":328.9063239},
{"learn":[1.186051852],"iteration":900,"passed_time":2962.980546,"remaining_time":325.56612},
{"learn":[1.185324706],"iteration":901,"passed_time":2965.814323,"remaining_time":322.2281637},
{"learn":[1.184758025],"iteration":902,"passed_time":2968.563804,"remaining_time":318.8822691},
{"learn":[1.184295739],"iteration":903,"passed_time":2971.326942,"remaining_time":315.5391443},
{"learn":[1.183594346],"iteration":904,"passed_time":2974.056731,"remaining_time":312.1938005},
{"learn":[1.183254301],"iteration":905,"passed_time":2976.771723,"remaining_time":308.8482803},
{"learn":[1.182526292],"iteration":906,"passed_time":2979.991299,"remaining_time":305.5558884},
{"learn":[1.181873545],"iteration":907,"passed_time":2983.497855,"remaining_time":302.2927343},
{"learn":[1.181315578],"iteration":908,"passed_time":2986.668027,"remaining_time":298.9953691},
{"learn":[1.180822813],"iteration":909,"passed_time":2989.519983,"remaining_time":295.6668115},
{"learn":[1.180397842],"iteration":910,"passed_time":2992.73516,"remaining_time":292.3747851},
{"learn":[1.179525667],"iteration":911,"passed_time":2996.015148,"remaining_time":289.089181},
{"learn":[1.178881693],"iteration":912,"passed_time":2998.912493,"remaining_time":285.7671269},
{"learn":[1.178285284],"iteration":913,"passed_time":3001.904634,"remaining_time":282.4549218},
{"learn":[1.177418015],"iteration":914,"passed_time":3004.932416,"remaining_time":279.1467271},
{"learn":[1.176963026],"iteration":915,"passed_time":3008.140908,"remaining_time":275.8557164},
{"learn":[1.176433043],"iteration":916,"passed_time":3011.422281,"remaining_time":272.5714823},
{"learn":[1.175997689],"iteration":917,"passed_time":3015.055937,"remaining_time":269.318722},
{"learn":[1.175306636],"iteration":918,"passed_time":3018.14251,"remaining_time":266.0169133},
{"learn":[1.175036084],"iteration":919,"passed_time":3021.280268,"remaining_time":262.7200233},
{"learn":[1.174749395],"iteration":920,"passed_time":3024.406182,"remaining_time":259.4224629},
{"learn":[1.174169154],"iteration":921,"passed_time":3027.536731,"remaining_time":256.125667},
{"learn":[1.173938612],"iteration":922,"passed_time":3030.314015,"remaining_time":252.7997607},
{"learn":[1.173464502],"iteration":923,"passed_time":3033.077813,"remaining_time":249.4739327},
{"learn":[1.17294213],"iteration":924,"passed_time":3035.966582,"remaining_time":246.1594526},
{"learn":[1.172621827],"iteration":925,"passed_time":3039.225405,"remaining_time":242.8754644},
{"learn":[1.171962257],"iteration":926,"passed_time":3042.296903,"remaining_time":239.5767788},
{"learn":[1.171520971],"iteration":927,"passed_time":3045.839391,"remaining_time":236.3151252},
{"learn":[1.170994504],"iteration":928,"passed_time":3048.550809,"remaining_time":232.9893514},
{"learn":[1.170387911],"iteration":929,"passed_time":3051.257221,"remaining_time":229.664522},
{"learn":[1.170059728],"iteration":930,"passed_time":3054.02785,"remaining_time":226.3457805},
{"learn":[1.169356615],"iteration":931,"passed_time":3056.929166,"remaining_time":223.0377503},
{"learn":[1.169112685],"iteration":932,"passed_time":3059.851703,"remaining_time":219.7321159},
{"learn":[1.16861344],"iteration":933,"passed_time":3062.593888,"remaining_time":216.4145574},
{"learn":[1.168217738],"iteration":934,"passed_time":3065.313048,"remaining_time":213.096629},
{"learn":[1.167700163],"iteration":935,"passed_time":3068.077468,"remaining_time":209.7830748},
{"learn":[1.166889202],"iteration":936,"passed_time":3070.913908,"remaining_time":206.4755349},
{"learn":[1.166598899],"iteration":937,"passed_time":3073.660799,"remaining_time":203.1630805},
{"learn":[1.166046986],"iteration":938,"passed_time":3076.435348,"remaining_time":199.8536275},
{"learn":[1.165462952],"iteration":939,"passed_time":3079.376132,"remaining_time":196.5559233},
{"learn":[1.16514086],"iteration":940,"passed_time":3082.340316,"remaining_time":193.2604449},
{"learn":[1.164665452],"iteration":941,"passed_time":3085.251166,"remaining_time":189.962386},
{"learn":[1.164220983],"iteration":942,"passed_time":3087.986666,"remaining_time":186.6545493},
{"learn":[1.163815787],"iteration":943,"passed_time":3090.853331,"remaining_time":183.3557061},
{"learn":[1.163242136],"iteration":944,"passed_time":3093.702597,"remaining_time":180.0567649},
{"learn":[1.162863626],"iteration":945,"passed_time":3096.395061,"remaining_time":176.7498238},
{"learn":[1.162384349],"iteration":946,"passed_time":3099.186919,"remaining_time":173.4497431},
{"learn":[1.161983453],"iteration":947,"passed_time":3102.12742,"remaining_time":170.158888},
{"learn":[1.161593945],"iteration":948,"passed_time":3105.020743,"remaining_time":166.8662359},
{"learn":[1.161115111],"iteration":949,"passed_time":3107.840675,"remaining_time":163.5705618},
{"learn":[1.160511918],"iteration":950,"passed_time":3110.513284,"remaining_time":160.2682975},
{"learn":[1.159701834],"iteration":951,"passed_time":3113.347557,"remaining_time":156.9755071},
{"learn":[1.159053444],"iteration":952,"passed_time":3116.148616,"remaining_time":153.6820409},
{"learn":[1.158397049],"iteration":953,"passed_time":3118.94387,"remaining_time":150.3893271},
{"learn":[1.157859161],"iteration":954,"passed_time":3121.733491,"remaining_time":147.0973896},
{"learn":[1.157511266],"iteration":955,"passed_time":3124.549667,"remaining_time":143.8077252},
{"learn":[1.157215283],"iteration":956,"passed_time":3127.300286,"remaining_time":140.5161048},
{"learn":[1.156901078],"iteration":957,"passed_time":3129.985642,"remaining_time":137.2227526},
{"learn":[1.156553898],"iteration":958,"passed_time":3132.972092,"remaining_time":133.9435409},
{"learn":[1.15611297],"iteration":959,"passed_time":3137.685961,"remaining_time":130.7369151},
{"learn":[1.155567826],"iteration":960,"passed_time":3143.18229,"remaining_time":127.5589067},
{"learn":[1.155076605],"iteration":961,"passed_time":3146.488016,"remaining_time":124.2895474},
{"learn":[1.154614369],"iteration":962,"passed_time":3149.581302,"remaining_time":121.0119504},
{"learn":[1.15402465],"iteration":963,"passed_time":3152.5267,"remaining_time":117.7292129},
{"learn":[1.153555296],"iteration":964,"passed_time":3155.401913,"remaining_time":114.444629},
{"learn":[1.153096456],"iteration":965,"passed_time":3158.238724,"remaining_time":111.159541},
{"learn":[1.152555424],"iteration":966,"passed_time":3161.161689,"remaining_time":107.8783203},
{"learn":[1.152225283],"iteration":967,"passed_time":3163.943919,"remaining_time":104.5931874},
{"learn":[1.151476334],"iteration":968,"passed_time":3166.873417,"remaining_time":101.3138038},
{"learn":[1.151176249],"iteration":969,"passed_time":3169.799866,"remaining_time":98.0350474},
{"learn":[1.150552047],"iteration":970,"passed_time":3172.634507,"remaining_time":94.75427466},
{"learn":[1.149950652],"iteration":971,"passed_time":3175.573819,"remaining_time":91.4774351},
{"learn":[1.149559904],"iteration":972,"passed_time":3178.4142,"remaining_time":88.19854409},
{"learn":[1.149166197],"iteration":973,"passed_time":3181.343087,"remaining_time":84.92291608},
{"learn":[1.148766299],"iteration":974,"passed_time":3184.116999,"remaining_time":81.64402561},
{"learn":[1.148625798],"iteration":975,"passed_time":3186.89622,"remaining_time":78.36630049},
{"learn":[1.14837277],"iteration":976,"passed_time":3190.186903,"remaining_time":75.1016364},
{"learn":[1.147806949],"iteration":977,"passed_time":3193.109636,"remaining_time":71.82864213},
{"learn":[1.147202536],"iteration":978,"passed_time":3196.141002,"remaining_time":68.55869361},
{"learn":[1.14672975],"iteration":979,"passed_time":3199.085791,"remaining_time":65.28746513},
{"learn":[1.146526972],"iteration":980,"passed_time":3202.457972,"remaining_time":62.02517989},
{"learn":[1.146002371],"iteration":981,"passed_time":3205.606694,"remaining_time":58.75857483},
{"learn":[1.145572433],"iteration":982,"passed_time":3208.357613,"remaining_time":55.48533004},
{"learn":[1.145216932],"iteration":983,"passed_time":3211.275101,"remaining_time":52.2158553},
{"learn":[1.144710108],"iteration":984,"passed_time":3214.373009,"remaining_time":48.94984278},
{"learn":[1.144316856],"iteration":985,"passed_time":3217.912883,"remaining_time":45.69044661},
{"learn":[1.143821676],"iteration":986,"passed_time":3221.611577,"remaining_time":42.43257397},
{"learn":[1.143280536],"iteration":987,"passed_time":3225.471048,"remaining_time":39.17576172},
{"learn":[1.142860049],"iteration":988,"passed_time":3228.930576,"remaining_time":35.91328245},
{"learn":[1.142401311],"iteration":989,"passed_time":3232.864583,"remaining_time":32.65519781},
{"learn":[1.142096548],"iteration":990,"passed_time":3236.719614,"remaining_time":29.39503182},
{"learn":[1.141766737],"iteration":991,"passed_time":3240.73287,"remaining_time":26.1349425},
{"learn":[1.141147688],"iteration":992,"passed_time":3244.383676,"remaining_time":22.8707812},
{"learn":[1.140622292],"iteration":993,"passed_time":3248.651877,"remaining_time":19.60956867},
{"learn":[1.139994228],"iteration":994,"passed_time":3252.650189,"remaining_time":16.34497583},
{"learn":[1.139278773],"iteration":995,"passed_time":3256.380033,"remaining_time":13.07783146},
{"learn":[1.1387902],"iteration":996,"passed_time":3260.237687,"remaining_time":9.810143491},
{"learn":[1.138384552],"iteration":997,"passed_time":3264.013674,"remaining_time":6.541109568},
{"learn":[1.137909916],"iteration":998,"passed_time":3267.709012,"remaining_time":3.270979992},
{"learn":[1.137457627],"iteration":999,"passed_time":3271.96023,"remaining_time":0}
]}